Workbook

Sheet Rankings
A1: Ranked opportunities - best entry, most expected growth, soonest setup
A2: Score 0-100 (weights on the Inputs tab). Growth = upside to the price target (12-month analyst horizon). Entry = upside vs. room down to the review level at today's price. Timing = pre-breakout chart score. A rank is a research order, not a buy order: check the STATUS, news and wash-sale locks.
A4: Rank | B4: Symbol | C4: Source | D4: SCORE | E4: Price | F4: Target | G4: Upside | H4: Review Level | I4: Room to Review | J4: Reward : Risk | K4: Setup Score | L4: Agreement | M4: Status
A5: 1 | B5: =IFERROR(INDEX('Rank Calc'!$A$5:$A$53,MATCH($A5,'Rank Calc'!$P$5:$P$53,0)),"") | C5: =IFERROR(INDEX('Rank Calc'!$B$5:$B$53,MATCH($A5,'Rank Calc'!$P$5:$P$53,0)),"") | D5: =IFERROR(INDEX('Rank Calc'!$O$5:$O$53,MATCH($A5,'Rank Calc'!$P$5:$P$53,0)),"") | E5: =IFERROR(INDEX('Rank Calc'!$C$5:$C$53,MATCH($A5,'Rank Calc'!$P$5:$P$53,0)),"") | F5: =IFERROR(INDEX('Rank Calc'!$D$5:$D$53,MATCH($A5,'Rank Calc'!$P$5:$P$53,0)),"") | G5: =IFERROR(INDEX('Rank Calc'!$I$5:$I$53,MATCH($A5,'Rank Calc'!$P$5:$P$53,0)),"") | H5: =IFERROR(INDEX('Rank Calc'!$E$5:$E$53,MATCH($A5,'Rank Calc'!$P$5:$P$53,0)),"") | I5: =IFERROR(INDEX('Rank Calc'!$J$5:$J$53,MATCH($A5,'Rank Calc'!$P$5:$P$53,0)),"") | J5: =IFERROR(INDEX('Rank Calc'!$K$5:$K$53,MATCH($A5,'Rank Calc'!$P$5:$P$53,0)),"") | K5: =IFERROR(INDEX('Rank Calc'!$G$5:$G$53,MATCH($A5,'Rank Calc'!$P$5:$P$53,0)),"") | L5: =IFERROR(INDEX('Rank Calc'!$F$5:$F$53,MATCH($A5,'Rank Calc'!$P$5:$P$53,0)),"") | M5: =IFERROR(INDEX('Rank Calc'!$H$5:$H$53,MATCH($A5,'Rank Calc'!$P$5:$P$53,0)),"")
A6: 2 | B6: =IFERROR(INDEX('Rank Calc'!$A$5:$A$53,MATCH($A6,'Rank Calc'!$P$5:$P$53,0)),"") | C6: =IFERROR(INDEX('Rank Calc'!$B$5:$B$53,MATCH($A6,'Rank Calc'!$P$5:$P$53,0)),"") | D6: =IFERROR(INDEX('Rank Calc'!$O$5:$O$53,MATCH($A6,'Rank Calc'!$P$5:$P$53,0)),"") | E6: =IFERROR(INDEX('Rank Calc'!$C$5:$C$53,MATCH($A6,'Rank Calc'!$P$5:$P$53,0)),"") | F6: =IFERROR(INDEX('Rank Calc'!$D$5:$D$53,MATCH($A6,'Rank Calc'!$P$5:$P$53,0)),"") | G6: =IFERROR(INDEX('Rank Calc'!$I$5:$I$53,MATCH($A6,'Rank Calc'!$P$5:$P$53,0)),"") | H6: =IFERROR(INDEX('Rank Calc'!$E$5:$E$53,MATCH($A6,'Rank Calc'!$P$5:$P$53,0)),"") | I6: =IFERROR(INDEX('Rank Calc'!$J$5:$J$53,MATCH($A6,'Rank Calc'!$P$5:$P$53,0)),"") | J6: =IFERROR(INDEX('Rank Calc'!$K$5:$K$53,MATCH($A6,'Rank Calc'!$P$5:$P$53,0)),"") | K6: =IFERROR(INDEX('Rank Calc'!$G$5:$G$53,MATCH($A6,'Rank Calc'!$P$5:$P$53,0)),"") | L6: =IFERROR(INDEX('Rank Calc'!$F$5:$F$53,MATCH($A6,'Rank Calc'!$P$5:$P$53,0)),"") | M6: =IFERROR(INDEX('Rank Calc'!$H$5:$H$53,MATCH($A6,'Rank Calc'!$P$5:$P$53,0)),"")
A7: 3 | B7: =IFERROR(INDEX('Rank Calc'!$A$5:$A$53,MATCH($A7,'Rank Calc'!$P$5:$P$53,0)),"") | C7: =IFERROR(INDEX('Rank Calc'!$B$5:$B$53,MATCH($A7,'Rank Calc'!$P$5:$P$53,0)),"") | D7: =IFERROR(INDEX('Rank Calc'!$O$5:$O$53,MATCH($A7,'Rank Calc'!$P$5:$P$53,0)),"") | E7: =IFERROR(INDEX('Rank Calc'!$C$5:$C$53,MATCH($A7,'Rank Calc'!$P$5:$P$53,0)),"") | F7: =IFERROR(INDEX('Rank Calc'!$D$5:$D$53,MATCH($A7,'Rank Calc'!$P$5:$P$53,0)),"") | G7: =IFERROR(INDEX('Rank Calc'!$I$5:$I$53,MATCH($A7,'Rank Calc'!$P$5:$P$53,0)),"") | H7: =IFERROR(INDEX('Rank Calc'!$E$5:$E$53,MATCH($A7,'Rank Calc'!$P$5:$P$53,0)),"") | I7: =IFERROR(INDEX('Rank Calc'!$J$5:$J$53,MATCH($A7,'Rank Calc'!$P$5:$P$53,0)),"") | J7: =IFERROR(INDEX('Rank Calc'!$K$5:$K$53,MATCH($A7,'Rank Calc'!$P$5:$P$53,0)),"") | K7: =IFERROR(INDEX('Rank Calc'!$G$5:$G$53,MATCH($A7,'Rank Calc'!$P$5:$P$53,0)),"") | L7: =IFERROR(INDEX('Rank Calc'!$F$5:$F$53,MATCH($A7,'Rank Calc'!$P$5:$P$53,0)),"") | M7: =IFERROR(INDEX('Rank Calc'!$H$5:$H$53,MATCH($A7,'Rank Calc'!$P$5:$P$53,0)),"")
A8: 4 | B8: =IFERROR(INDEX('Rank Calc'!$A$5:$A$53,MATCH($A8,'Rank Calc'!$P$5:$P$53,0)),"") | C8: =IFERROR(INDEX('Rank Calc'!$B$5:$B$53,MATCH($A8,'Rank Calc'!$P$5:$P$53,0)),"") | D8: =IFERROR(INDEX('Rank Calc'!$O$5:$O$53,MATCH($A8,'Rank Calc'!$P$5:$P$53,0)),"") | E8: =IFERROR(INDEX('Rank Calc'!$C$5:$C$53,MATCH($A8,'Rank Calc'!$P$5:$P$53,0)),"") | F8: =IFERROR(INDEX('Rank Calc'!$D$5:$D$53,MATCH($A8,'Rank Calc'!$P$5:$P$53,0)),"") | G8: =IFERROR(INDEX('Rank Calc'!$I$5:$I$53,MATCH($A8,'Rank Calc'!$P$5:$P$53,0)),"") | H8: =IFERROR(INDEX('Rank Calc'!$E$5:$E$53,MATCH($A8,'Rank Calc'!$P$5:$P$53,0)),"") | I8: =IFERROR(INDEX('Rank Calc'!$J$5:$J$53,MATCH($A8,'Rank Calc'!$P$5:$P$53,0)),"") | J8: =IFERROR(INDEX('Rank Calc'!$K$5:$K$53,MATCH($A8,'Rank Calc'!$P$5:$P$53,0)),"") | K8: =IFERROR(INDEX('Rank Calc'!$G$5:$G$53,MATCH($A8,'Rank Calc'!$P$5:$P$53,0)),"") | L8: =IFERROR(INDEX('Rank Calc'!$F$5:$F$53,MATCH($A8,'Rank Calc'!$P$5:$P$53,0)),"") | M8: =IFERROR(INDEX('Rank Calc'!$H$5:$H$53,MATCH($A8,'Rank Calc'!$P$5:$P$53,0)),"")
A9: 5 | B9: =IFERROR(INDEX('Rank Calc'!$A$5:$A$53,MATCH($A9,'Rank Calc'!$P$5:$P$53,0)),"") | C9: =IFERROR(INDEX('Rank Calc'!$B$5:$B$53,MATCH($A9,'Rank Calc'!$P$5:$P$53,0)),"") | D9: =IFERROR(INDEX('Rank Calc'!$O$5:$O$53,MATCH($A9,'Rank Calc'!$P$5:$P$53,0)),"") | E9: =IFERROR(INDEX('Rank Calc'!$C$5:$C$53,MATCH($A9,'Rank Calc'!$P$5:$P$53,0)),"") | F9: =IFERROR(INDEX('Rank Calc'!$D$5:$D$53,MATCH($A9,'Rank Calc'!$P$5:$P$53,0)),"") | G9: =IFERROR(INDEX('Rank Calc'!$I$5:$I$53,MATCH($A9,'Rank Calc'!$P$5:$P$53,0)),"") | H9: =IFERROR(INDEX('Rank Calc'!$E$5:$E$53,MATCH($A9,'Rank Calc'!$P$5:$P$53,0)),"") | I9: =IFERROR(INDEX('Rank Calc'!$J$5:$J$53,MATCH($A9,'Rank Calc'!$P$5:$P$53,0)),"") | J9: =IFERROR(INDEX('Rank Calc'!$K$5:$K$53,MATCH($A9,'Rank Calc'!$P$5:$P$53,0)),"") | K9: =IFERROR(INDEX('Rank Calc'!$G$5:$G$53,MATCH($A9,'Rank Calc'!$P$5:$P$53,0)),"") | L9: =IFERROR(INDEX('Rank Calc'!$F$5:$F$53,MATCH($A9,'Rank Calc'!$P$5:$P$53,0)),"") | M9: =IFERROR(INDEX('Rank Calc'!$H$5:$H$53,MATCH($A9,'Rank Calc'!$P$5:$P$53,0)),"")
A10: 6 | B10: =IFERROR(INDEX('Rank Calc'!$A$5:$A$53,MATCH($A10,'Rank Calc'!$P$5:$P$53,0)),"") | C10: =IFERROR(INDEX('Rank Calc'!$B$5:$B$53,MATCH($A10,'Rank Calc'!$P$5:$P$53,0)),"") | D10: =IFERROR(INDEX('Rank Calc'!$O$5:$O$53,MATCH($A10,'Rank Calc'!$P$5:$P$53,0)),"") | E10: =IFERROR(INDEX('Rank Calc'!$C$5:$C$53,MATCH($A10,'Rank Calc'!$P$5:$P$53,0)),"") | F10: =IFERROR(INDEX('Rank Calc'!$D$5:$D$53,MATCH($A10,'Rank Calc'!$P$5:$P$53,0)),"") | G10: =IFERROR(INDEX('Rank Calc'!$I$5:$I$53,MATCH($A10,'Rank Calc'!$P$5:$P$53,0)),"") | H10: =IFERROR(INDEX('Rank Calc'!$E$5:$E$53,MATCH($A10,'Rank Calc'!$P$5:$P$53,0)),"") | I10: =IFERROR(INDEX('Rank Calc'!$J$5:$J$53,MATCH($A10,'Rank Calc'!$P$5:$P$53,0)),"") | J10: =IFERROR(INDEX('Rank Calc'!$K$5:$K$53,MATCH($A10,'Rank Calc'!$P$5:$P$53,0)),"") | K10: =IFERROR(INDEX('Rank Calc'!$G$5:$G$53,MATCH($A10,'Rank Calc'!$P$5:$P$53,0)),"") | L10: =IFERROR(INDEX('Rank Calc'!$F$5:$F$53,MATCH($A10,'Rank Calc'!$P$5:$P$53,0)),"") | M10: =IFERROR(INDEX('Rank Calc'!$H$5:$H$53,MATCH($A10,'Rank Calc'!$P$5:$P$53,0)),"")
A11: 7 | B11: =IFERROR(INDEX('Rank Calc'!$A$5:$A$53,MATCH($A11,'Rank Calc'!$P$5:$P$53,0)),"") | C11: =IFERROR(INDEX('Rank Calc'!$B$5:$B$53,MATCH($A11,'Rank Calc'!$P$5:$P$53,0)),"") | D11: =IFERROR(INDEX('Rank Calc'!$O$5:$O$53,MATCH($A11,'Rank Calc'!$P$5:$P$53,0)),"") | E11: =IFERROR(INDEX('Rank Calc'!$C$5:$C$53,MATCH($A11,'Rank Calc'!$P$5:$P$53,0)),"") | F11: =IFERROR(INDEX('Rank Calc'!$D$5:$D$53,MATCH($A11,'Rank Calc'!$P$5:$P$53,0)),"") | G11: =IFERROR(INDEX('Rank Calc'!$I$5:$I$53,MATCH($A11,'Rank Calc'!$P$5:$P$53,0)),"") | H11: =IFERROR(INDEX('Rank Calc'!$E$5:$E$53,MATCH($A11,'Rank Calc'!$P$5:$P$53,0)),"") | I11: =IFERROR(INDEX('Rank Calc'!$J$5:$J$53,MATCH($A11,'Rank Calc'!$P$5:$P$53,0)),"") | J11: =IFERROR(INDEX('Rank Calc'!$K$5:$K$53,MATCH($A11,'Rank Calc'!$P$5:$P$53,0)),"") | K11: =IFERROR(INDEX('Rank Calc'!$G$5:$G$53,MATCH($A11,'Rank Calc'!$P$5:$P$53,0)),"") | L11: =IFERROR(INDEX('Rank Calc'!$F$5:$F$53,MATCH($A11,'Rank Calc'!$P$5:$P$53,0)),"") | M11: =IFERROR(INDEX('Rank Calc'!$H$5:$H$53,MATCH($A11,'Rank Calc'!$P$5:$P$53,0)),"")
A12: 8 | B12: =IFERROR(INDEX('Rank Calc'!$A$5:$A$53,MATCH($A12,'Rank Calc'!$P$5:$P$53,0)),"") | C12: =IFERROR(INDEX('Rank Calc'!$B$5:$B$53,MATCH($A12,'Rank Calc'!$P$5:$P$53,0)),"") | D12: =IFERROR(INDEX('Rank Calc'!$O$5:$O$53,MATCH($A12,'Rank Calc'!$P$5:$P$53,0)),"") | E12: =IFERROR(INDEX('Rank Calc'!$C$5:$C$53,MATCH($A12,'Rank Calc'!$P$5:$P$53,0)),"") | F12: =IFERROR(INDEX('Rank Calc'!$D$5:$D$53,MATCH($A12,'Rank Calc'!$P$5:$P$53,0)),"") | G12: =IFERROR(INDEX('Rank Calc'!$I$5:$I$53,MATCH($A12,'Rank Calc'!$P$5:$P$53,0)),"") | H12: =IFERROR(INDEX('Rank Calc'!$E$5:$E$53,MATCH($A12,'Rank Calc'!$P$5:$P$53,0)),"") | I12: =IFERROR(INDEX('Rank Calc'!$J$5:$J$53,MATCH($A12,'Rank Calc'!$P$5:$P$53,0)),"") | J12: =IFERROR(INDEX('Rank Calc'!$K$5:$K$53,MATCH($A12,'Rank Calc'!$P$5:$P$53,0)),"") | K12: =IFERROR(INDEX('Rank Calc'!$G$5:$G$53,MATCH($A12,'Rank Calc'!$P$5:$P$53,0)),"") | L12: =IFERROR(INDEX('Rank Calc'!$F$5:$F$53,MATCH($A12,'Rank Calc'!$P$5:$P$53,0)),"") | M12: =IFERROR(INDEX('Rank Calc'!$H$5:$H$53,MATCH($A12,'Rank Calc'!$P$5:$P$53,0)),"")
A13: 9 | B13: =IFERROR(INDEX('Rank Calc'!$A$5:$A$53,MATCH($A13,'Rank Calc'!$P$5:$P$53,0)),"") | C13: =IFERROR(INDEX('Rank Calc'!$B$5:$B$53,MATCH($A13,'Rank Calc'!$P$5:$P$53,0)),"") | D13: =IFERROR(INDEX('Rank Calc'!$O$5:$O$53,MATCH($A13,'Rank Calc'!$P$5:$P$53,0)),"") | E13: =IFERROR(INDEX('Rank Calc'!$C$5:$C$53,MATCH($A13,'Rank Calc'!$P$5:$P$53,0)),"") | F13: =IFERROR(INDEX('Rank Calc'!$D$5:$D$53,MATCH($A13,'Rank Calc'!$P$5:$P$53,0)),"") | G13: =IFERROR(INDEX('Rank Calc'!$I$5:$I$53,MATCH($A13,'Rank Calc'!$P$5:$P$53,0)),"") | H13: =IFERROR(INDEX('Rank Calc'!$E$5:$E$53,MATCH($A13,'Rank Calc'!$P$5:$P$53,0)),"") | I13: =IFERROR(INDEX('Rank Calc'!$J$5:$J$53,MATCH($A13,'Rank Calc'!$P$5:$P$53,0)),"") | J13: =IFERROR(INDEX('Rank Calc'!$K$5:$K$53,MATCH($A13,'Rank Calc'!$P$5:$P$53,0)),"") | K13: =IFERROR(INDEX('Rank Calc'!$G$5:$G$53,MATCH($A13,'Rank Calc'!$P$5:$P$53,0)),"") | L13: =IFERROR(INDEX('Rank Calc'!$F$5:$F$53,MATCH($A13,'Rank Calc'!$P$5:$P$53,0)),"") | M13: =IFERROR(INDEX('Rank Calc'!$H$5:$H$53,MATCH($A13,'Rank Calc'!$P$5:$P$53,0)),"")
A14: 10 | B14: =IFERROR(INDEX('Rank Calc'!$A$5:$A$53,MATCH($A14,'Rank Calc'!$P$5:$P$53,0)),"") | C14: =IFERROR(INDEX('Rank Calc'!$B$5:$B$53,MATCH($A14,'Rank Calc'!$P$5:$P$53,0)),"") | D14: =IFERROR(INDEX('Rank Calc'!$O$5:$O$53,MATCH($A14,'Rank Calc'!$P$5:$P$53,0)),"") | E14: =IFERROR(INDEX('Rank Calc'!$C$5:$C$53,MATCH($A14,'Rank Calc'!$P$5:$P$53,0)),"") | F14: =IFERROR(INDEX('Rank Calc'!$D$5:$D$53,MATCH($A14,'Rank Calc'!$P$5:$P$53,0)),"") | G14: =IFERROR(INDEX('Rank Calc'!$I$5:$I$53,MATCH($A14,'Rank Calc'!$P$5:$P$53,0)),"") | H14: =IFERROR(INDEX('Rank Calc'!$E$5:$E$53,MATCH($A14,'Rank Calc'!$P$5:$P$53,0)),"") | I14: =IFERROR(INDEX('Rank Calc'!$J$5:$J$53,MATCH($A14,'Rank Calc'!$P$5:$P$53,0)),"") | J14: =IFERROR(INDEX('Rank Calc'!$K$5:$K$53,MATCH($A14,'Rank Calc'!$P$5:$P$53,0)),"") | K14: =IFERROR(INDEX('Rank Calc'!$G$5:$G$53,MATCH($A14,'Rank Calc'!$P$5:$P$53,0)),"") | L14: =IFERROR(INDEX('Rank Calc'!$F$5:$F$53,MATCH($A14,'Rank Calc'!$P$5:$P$53,0)),"") | M14: =IFERROR(INDEX('Rank Calc'!$H$5:$H$53,MATCH($A14,'Rank Calc'!$P$5:$P$53,0)),"")
A15: 11 | B15: =IFERROR(INDEX('Rank Calc'!$A$5:$A$53,MATCH($A15,'Rank Calc'!$P$5:$P$53,0)),"") | C15: =IFERROR(INDEX('Rank Calc'!$B$5:$B$53,MATCH($A15,'Rank Calc'!$P$5:$P$53,0)),"") | D15: =IFERROR(INDEX('Rank Calc'!$O$5:$O$53,MATCH($A15,'Rank Calc'!$P$5:$P$53,0)),"") | E15: =IFERROR(INDEX('Rank Calc'!$C$5:$C$53,MATCH($A15,'Rank Calc'!$P$5:$P$53,0)),"") | F15: =IFERROR(INDEX('Rank Calc'!$D$5:$D$53,MATCH($A15,'Rank Calc'!$P$5:$P$53,0)),"") | G15: =IFERROR(INDEX('Rank Calc'!$I$5:$I$53,MATCH($A15,'Rank Calc'!$P$5:$P$53,0)),"") | H15: =IFERROR(INDEX('Rank Calc'!$E$5:$E$53,MATCH($A15,'Rank Calc'!$P$5:$P$53,0)),"") | I15: =IFERROR(INDEX('Rank Calc'!$J$5:$J$53,MATCH($A15,'Rank Calc'!$P$5:$P$53,0)),"") | J15: =IFERROR(INDEX('Rank Calc'!$K$5:$K$53,MATCH($A15,'Rank Calc'!$P$5:$P$53,0)),"") | K15: =IFERROR(INDEX('Rank Calc'!$G$5:$G$53,MATCH($A15,'Rank Calc'!$P$5:$P$53,0)),"") | L15: =IFERROR(INDEX('Rank Calc'!$F$5:$F$53,MATCH($A15,'Rank Calc'!$P$5:$P$53,0)),"") | M15: =IFERROR(INDEX('Rank Calc'!$H$5:$H$53,MATCH($A15,'Rank Calc'!$P$5:$P$53,0)),"")
A16: 12 | B16: =IFERROR(INDEX('Rank Calc'!$A$5:$A$53,MATCH($A16,'Rank Calc'!$P$5:$P$53,0)),"") | C16: =IFERROR(INDEX('Rank Calc'!$B$5:$B$53,MATCH($A16,'Rank Calc'!$P$5:$P$53,0)),"") | D16: =IFERROR(INDEX('Rank Calc'!$O$5:$O$53,MATCH($A16,'Rank Calc'!$P$5:$P$53,0)),"") | E16: =IFERROR(INDEX('Rank Calc'!$C$5:$C$53,MATCH($A16,'Rank Calc'!$P$5:$P$53,0)),"") | F16: =IFERROR(INDEX('Rank Calc'!$D$5:$D$53,MATCH($A16,'Rank Calc'!$P$5:$P$53,0)),"") | G16: =IFERROR(INDEX('Rank Calc'!$I$5:$I$53,MATCH($A16,'Rank Calc'!$P$5:$P$53,0)),"") | H16: =IFERROR(INDEX('Rank Calc'!$E$5:$E$53,MATCH($A16,'Rank Calc'!$P$5:$P$53,0)),"") | I16: =IFERROR(INDEX('Rank Calc'!$J$5:$J$53,MATCH($A16,'Rank Calc'!$P$5:$P$53,0)),"") | J16: =IFERROR(INDEX('Rank Calc'!$K$5:$K$53,MATCH($A16,'Rank Calc'!$P$5:$P$53,0)),"") | K16: =IFERROR(INDEX('Rank Calc'!$G$5:$G$53,MATCH($A16,'Rank Calc'!$P$5:$P$53,0)),"") | L16: =IFERROR(INDEX('Rank Calc'!$F$5:$F$53,MATCH($A16,'Rank Calc'!$P$5:$P$53,0)),"") | M16: =IFERROR(INDEX('Rank Calc'!$H$5:$H$53,MATCH($A16,'Rank Calc'!$P$5:$P$53,0)),"")
... A53: 49 | B53: =IFERROR(INDEX('Rank Calc'!$A$5:$A$53,MATCH($A53,'Rank Calc'!$P$5:$P$53,0)),"") | C53: =IFERROR(INDEX('Rank Calc'!$B$5:$B$53,MATCH($A53,'Rank Calc'!$P$5:$P$53,0)),"") | D53: =IFERROR(INDEX('Rank Calc'!$O$5:$O$53,MATCH($A53,'Rank Calc'!$P$5:$P$53,0)),"") | E53: =IFERROR(INDEX('Rank Calc'!$C$5:$C$53,MATCH($A53,'Rank Calc'!$P$5:$P$53,0)),"") | F53: =IFERROR(INDEX('Rank Calc'!$D$5:$D$53,MATCH($A53,'Rank Calc'!$P$5:$P$53,0)),"") | G53: =IFERROR(INDEX('Rank Calc'!$I$5:$I$53,MATCH($A53,'Rank Calc'!$P$5:$P$53,0)),"") | H53: =IFERROR(INDEX('Rank Calc'!$E$5:$E$53,MATCH($A53,'Rank Calc'!$P$5:$P$53,0)),"") | I53: =IFERROR(INDEX('Rank Calc'!$J$5:$J$53,MATCH($A53,'Rank Calc'!$P$5:$P$53,0)),"") | J53: =IFERROR(INDEX('Rank Calc'!$K$5:$K$53,MATCH($A53,'Rank Calc'!$P$5:$P$53,0)),"") | K53: =IFERROR(INDEX('Rank Calc'!$G$5:$G$53,MATCH($A53,'Rank Calc'!$P$5:$P$53,0)),"") | L53: =IFERROR(INDEX('Rank Calc'!$F$5:$F$53,MATCH($A53,'Rank Calc'!$P$5:$P$53,0)),"") | M53: =IFERROR(INDEX('Rank Calc'!$H$5:$H$53,MATCH($A53,'Rank Calc'!$P$5:$P$53,0)),"")

Sheet Holdings
A1: Joint Account (••••5343) - Holdings, Price Targets and Sell Targets
A2: Blue columns are inputs (broker snapshot + routine targets). Green-header columns are formulas. Sell targets are guides for Ryan; the agent never trades the joint account.
A3: Price used: | B3: =Inputs!$B$6 | C3: Close 2026-10-29 | D3: =Inputs!$B$5 | F3: Not priced (check in the app): EPIX^
A5: Symbol | B5: Company | C5: Type | D5: Sector | E5: Shares | F5: Avg Cost | G5: Price | H5: After-hrs | I5: 50-day SMA | J5: 200-day SMA | K5: 60-day Low | L5: 60-day High | M5: 52-wk High | N5: Tgt: Fundamental | O5: Tgt: Robinhood | P5: Tgt: Analysts | Q5: FINAL Price Target | R5: Target Agreement | S5: Valuation | T5: Disruption | U5: Next Earnings | V5: Price Used | W5: Market Value | X5: Cost Basis | Y5: Unrealized P/L $ | Z5: P/L % | AA5: Weight | AB5: After-hrs Move | AC5: vs 50-day | AD5: vs 200-day | AE5: Off 52-wk High | AF5: Upside to Target | AG5: SELL TARGET 1 (trim) | AH5: SELL TARGET 2 (trim) | AI5: Shares per Trim | AJ5: Proceeds at T1 | AK5: DOWNSIDE REVIEW LEVEL | AL5: Cushion to Review | AM5: Trailing Stop (if green) | AN5: Reward : Risk | AO5: ACTION | AP5: RANK | AQ5: Notes
A6: META | B6: Meta Platforms | C6: Stock | D6: Internet | E6: 25.982426 | F6: 631.15 | G6: 624.52 | H6: 618.49 | I6: 668.6 | J6: 632.11 | K6: 537.27 | L6: 779.82 | M6: 779.82 | N6: 890.02 | O6: 850.51 | P6: 840 | Q6: 850.51 | R6: HIGH | S6: FAIR -2% (med) | T6: INNOVATING | U6: n/a | V6: =IF(AND(Inputs!$B$6="After-hours",N(H6)>0),H6,G6) | W6: =E6*V6 | X6: =E6*F6 | Y6: =W6-X6 | Z6: =IFERROR(Y6/X6,"") | AA6: =W6/$W$27 | AB6: =IFERROR(IF(N(H6)>0,H6/G6-1,""),"") | AC6: =IFERROR(V6/I6-1,"") | AD6: =IFERROR(V6/J6-1,"") | AE6: =IFERROR(V6/M6-1,"") | AF6: =IF(N(Q6)>0,Q6/V6-1,"") | AG6: =IF(N(Q6)>0,Q6*Inputs!$B$7,"") | AH6: =IF(N(Q6)>0,Q6*(1+Inputs!$B$8),"") | AI6: =E6*Inputs!$B$9 | AJ6: =IF(N(AG6)>0,AI6*AG6,"") | AK6: =MAX(K6*(1-Inputs!$B$10),F6*(1-IF(ISNUMBER(SEARCH("Lev",C6)),Inputs!$B$12,Inputs!$B$11))) | AL6: =IFERROR(V6/AK6-1,"") | AM6: =IF(V6>=F6/(1-Inputs!$B$13),MAX(F6,L6*(1-Inputs!$B$13)),"not green yet") | AN6: =IF(AND(N(Q6)>0,V6>AK6,AG6>V6),(AG6-V6)/(V6-AK6),"") | AO6: =IF(W6<100,"DUST: clean up",IF(V6<AK6,"REVIEW: below support / max loss",IF(AND(N(Q6)>0,V6>=AH6),"SELL 2nd TRIM, trail the rest",IF(AND(N(Q6)>0,V6>=AG6),"TRIM 1/3 + thesis re-check",IF(AA6>IF(ISNUMBER(SEARCH("Lev",C6)),Inputs!$B$15,Inputs!$B$14),"OVERWEIGHT: trim to cap",IF(IF(ISNUMBER(U6),AND(U6>Inputs!$B$5,U6-Inputs!$B$5<=Inputs!$B$16),FALSE),"HOLD: earnings soon",IF(N(Q6)=0,"HOLD: no target","HOLD"))))))) | AP6: =IFERROR(INDEX('Rank Calc'!$P$5:$P$53,MATCH($A6,'Rank Calc'!$A$5:$A$53,0)),"") | AQ6: Already held (~15% of the joint account).
A7: AMZN | B7: Amazon | C7: Stock | D7: Internet retail / cloud | E7: 61.916672 | F7: 229.2 | G7: 243.79 | H7: 226.96 | I7: 254.89 | J7: 243.44 | K7: 244.3 | L7: 280.14 | M7: 287.2 | N7: 440.05 | O7: 333.68 | P7: 350 | Q7: 350 | R7: MED | S7: DEEP VALUE +100% (low) | T7: INNOVATING | U7: 46324 | V7: =IF(AND(Inputs!$B$6="After-hours",N(H7)>0),H7,G7) | W7: =E7*V7 | X7: =E7*F7 | Y7: =W7-X7 | Z7: =IFERROR(Y7/X7,"") | AA7: =W7/$W$27 | AB7: =IFERROR(IF(N(H7)>0,H7/G7-1,""),"") | AC7: =IFERROR(V7/I7-1,"") | AD7: =IFERROR(V7/J7-1,"") | AE7: =IFERROR(V7/M7-1,"") | AF7: =IF(N(Q7)>0,Q7/V7-1,"") | AG7: =IF(N(Q7)>0,Q7*Inputs!$B$7,"") | AH7: =IF(N(Q7)>0,Q7*(1+Inputs!$B$8),"") | AI7: =E7*Inputs!$B$9 | AJ7: =IF(N(AG7)>0,AI7*AG7,"") | AK7: =MAX(K7*(1-Inputs!$B$10),F7*(1-IF(ISNUMBER(SEARCH("Lev",C7)),Inputs!$B$12,Inputs!$B$11))) | AL7: =IFERROR(V7/AK7-1,"") | AM7: =IF(V7>=F7/(1-Inputs!$B$13),MAX(F7,L7*(1-Inputs!$B$13)),"not green yet") | AN7: =IF(AND(N(Q7)>0,V7>AK7,AG7>V7),(AG7-V7)/(V7-AK7),"") | AO7: =IF(W7<100,"DUST: clean up",IF(V7<AK7,"REVIEW: below support / max loss",IF(AND(N(Q7)>0,V7>=AH7),"SELL 2nd TRIM, trail the rest",IF(AND(N(Q7)>0,V7>=AG7),"TRIM 1/3 + thesis re-check",IF(AA7>IF(ISNUMBER(SEARCH("Lev",C7)),Inputs!$B$15,Inputs!$B$14),"OVERWEIGHT: trim to cap",IF(IF(ISNUMBER(U7),AND(U7>Inputs!$B$5,U7-Inputs!$B$5<=Inputs!$B$16),FALSE),"HOLD: earnings soon",IF(N(Q7)=0,"HOLD: no target","HOLD"))))))) | AP7: =IFERROR(INDEX('Rank Calc'!$P$5:$P$53,MATCH($A7,'Rank Calc'!$A$5:$A$53,0)),"") | AQ7: Q3 EPS 1.89 vs 1.97 est (miss); -6.9% after hours. Below 60-day low AH.
A8: SOXL | B8: Direxion Semis 3x Bull | C8: 3x Lev ETF | D8: Semiconductors | E8: 145 | F8: 86.37 | G8: 102.39 | H8: 87.39 | I8: 122.07 | J8: 124.17 | K8: 80.22 | L8: 169.83 | M8: 302 | Q8: 122.07 | R8: TECH (50-day) | S8: n/a | T8: N/A | U8: n/a | V8: =IF(AND(Inputs!$B$6="After-hours",N(H8)>0),H8,G8) | W8: =E8*V8 | X8: =E8*F8 | Y8: =W8-X8 | Z8: =IFERROR(Y8/X8,"") | AA8: =W8/$W$27 | AB8: =IFERROR(IF(N(H8)>0,H8/G8-1,""),"") | AC8: =IFERROR(V8/I8-1,"") | AD8: =IFERROR(V8/J8-1,"") | AE8: =IFERROR(V8/M8-1,"") | AF8: =IF(N(Q8)>0,Q8/V8-1,"") | AG8: =IF(N(Q8)>0,Q8*Inputs!$B$7,"") | AH8: =IF(N(Q8)>0,Q8*(1+Inputs!$B$8),"") | AI8: =E8*Inputs!$B$9 | AJ8: =IF(N(AG8)>0,AI8*AG8,"") | AK8: =MAX(K8*(1-Inputs!$B$10),F8*(1-IF(ISNUMBER(SEARCH("Lev",C8)),Inputs!$B$12,Inputs!$B$11))) | AL8: =IFERROR(V8/AK8-1,"") | AM8: =IF(V8>=F8/(1-Inputs!$B$13),MAX(F8,L8*(1-Inputs!$B$13)),"not green yet") | AN8: =IF(AND(N(Q8)>0,V8>AK8,AG8>V8),(AG8-V8)/(V8-AK8),"") | AO8: =IF(W8<100,"DUST: clean up",IF(V8<AK8,"REVIEW: below support / max loss",IF(AND(N(Q8)>0,V8>=AH8),"SELL 2nd TRIM, trail the rest",IF(AND(N(Q8)>0,V8>=AG8),"TRIM 1/3 + thesis re-check",IF(AA8>IF(ISNUMBER(SEARCH("Lev",C8)),Inputs!$B$15,Inputs!$B$14),"OVERWEIGHT: trim to cap",IF(IF(ISNUMBER(U8),AND(U8>Inputs!$B$5,U8-Inputs!$B$5<=Inputs!$B$16),FALSE),"HOLD: earnings soon",IF(N(Q8)=0,"HOLD: no target","HOLD"))))))) | AP8: =IFERROR(INDEX('Rank Calc'!$P$5:$P$53,MATCH($A8,'Rank Calc'!$A$5:$A$53,0)),"") | AQ8: 3x daily leverage, decays in chop. No analyst target: target = 50-day SMA (first resistance). -14.6% AH.
A9: SPCX | B9: SpaceX | C9: Stock | D9: Space / telecom / AI | E9: 65 | F9: 154.95 | G9: 143.89 | H9: 140.71 | I9: 149.57 | J9: 147.94 | K9: 105.11 | L9: 176.42 | M9: 225.64 | O9: 256 | P9: 240 | Q9: 248 | R9: MED | S9: n/a | T9: N/A | U9: n/a | V9: =IF(AND(Inputs!$B$6="After-hours",N(H9)>0),H9,G9) | W9: =E9*V9 | X9: =E9*F9 | Y9: =W9-X9 | Z9: =IFERROR(Y9/X9,"") | AA9: =W9/$W$27 | AB9: =IFERROR(IF(N(H9)>0,H9/G9-1,""),"") | AC9: =IFERROR(V9/I9-1,"") | AD9: =IFERROR(V9/J9-1,"") | AE9: =IFERROR(V9/M9-1,"") | AF9: =IF(N(Q9)>0,Q9/V9-1,"") | AG9: =IF(N(Q9)>0,Q9*Inputs!$B$7,"") | AH9: =IF(N(Q9)>0,Q9*(1+Inputs!$B$8),"") | AI9: =E9*Inputs!$B$9 | AJ9: =IF(N(AG9)>0,AI9*AG9,"") | AK9: =MAX(K9*(1-Inputs!$B$10),F9*(1-IF(ISNUMBER(SEARCH("Lev",C9)),Inputs!$B$12,Inputs!$B$11))) | AL9: =IFERROR(V9/AK9-1,"") | AM9: =IF(V9>=F9/(1-Inputs!$B$13),MAX(F9,L9*(1-Inputs!$B$13)),"not green yet") | AN9: =IF(AND(N(Q9)>0,V9>AK9,AG9>V9),(AG9-V9)/(V9-AK9),"") | AO9: =IF(W9<100,"DUST: clean up",IF(V9<AK9,"REVIEW: below support / max loss",IF(AND(N(Q9)>0,V9>=AH9),"SELL 2nd TRIM, trail the rest",IF(AND(N(Q9)>0,V9>=AG9),"TRIM 1/3 + thesis re-check",IF(AA9>IF(ISNUMBER(SEARCH("Lev",C9)),Inputs!$B$15,Inputs!$B$14),"OVERWEIGHT: trim to cap",IF(IF(ISNUMBER(U9),AND(U9>Inputs!$B$5,U9-Inputs!$B$5<=Inputs!$B$16),FALSE),"HOLD: earnings soon",IF(N(Q9)=0,"HOLD: no target","HOLD"))))))) | AP9: =IFERROR(INDEX('Rank Calc'!$P$5:$P$53,MATCH($A9,'Rank Calc'!$A$5:$A$53,0)),"")
A10: NBIS | B10: Nebius Group | C10: Stock | D10: AI cloud | E10: 46 | F10: 162.87 | G10: 171.99 | H10: 164.33 | I10: 211.23 | J10: 177.28 | K10: 149.48 | L10: 280.83 | M10: 299.86 | O10: 286.71 | P10: 250 | Q10: 268.36 | R10: MED | S10: EXPENSIVE -50% (low) | T10: DISRUPTOR | U10: 46336 | V10: =IF(AND(Inputs!$B$6="After-hours",N(H10)>0),H10,G10) | W10: =E10*V10 | X10: =E10*F10 | Y10: =W10-X10 | Z10: =IFERROR(Y10/X10,"") | AA10: =W10/$W$27 | AB10: =IFERROR(IF(N(H10)>0,H10/G10-1,""),"") | AC10: =IFERROR(V10/I10-1,"") | AD10: =IFERROR(V10/J10-1,"") | AE10: =IFERROR(V10/M10-1,"") | AF10: =IF(N(Q10)>0,Q10/V10-1,"") | AG10: =IF(N(Q10)>0,Q10*Inputs!$B$7,"") | AH10: =IF(N(Q10)>0,Q10*(1+Inputs!$B$8),"") | AI10: =E10*Inputs!$B$9 | AJ10: =IF(N(AG10)>0,AI10*AG10,"") | AK10: =MAX(K10*(1-Inputs!$B$10),F10*(1-IF(ISNUMBER(SEARCH("Lev",C10)),Inputs!$B$12,Inputs!$B$11))) | AL10: =IFERROR(V10/AK10-1,"") | AM10: =IF(V10>=F10/(1-Inputs!$B$13),MAX(F10,L10*(1-Inputs!$B$13)),"not green yet") | AN10: =IF(AND(N(Q10)>0,V10>AK10,AG10>V10),(AG10-V10)/(V10-AK10),"") | AO10: =IF(W10<100,"DUST: clean up",IF(V10<AK10,"REVIEW: below support / max loss",IF(AND(N(Q10)>0,V10>=AH10),"SELL 2nd TRIM, trail the rest",IF(AND(N(Q10)>0,V10>=AG10),"TRIM 1/3 + thesis re-check",IF(AA10>IF(ISNUMBER(SEARCH("Lev",C10)),Inputs!$B$15,Inputs!$B$14),"OVERWEIGHT: trim to cap",IF(IF(ISNUMBER(U10),AND(U10>Inputs!$B$5,U10-Inputs!$B$5<=Inputs!$B$16),FALSE),"HOLD: earnings soon",IF(N(Q10)=0,"HOLD: no target","HOLD"))))))) | AP10: =IFERROR(INDEX('Rank Calc'!$P$5:$P$53,MATCH($A10,'Rank Calc'!$A$5:$A$53,0)),"") | AQ10: Earnings date unverified.
A11: MPWR | B11: Monolithic Power | C11: Stock | D11: Semiconductors | E11: 6 | F11: 1165.4 | G11: 1198.81 | H11: 1190.01 | I11: 1276.92 | J11: 1315.16 | K11: 1126.57 | L11: 1491.64 | M11: 1714.09 | N11: 1870.2 | O11: 1807.46 | Q11: 1838.83 | R11: HIGH | S11: RICH -23% (low) | T11: INNOVATING | U11: 46324 | V11: =IF(AND(Inputs!$B$6="After-hours",N(H11)>0),H11,G11) | W11: =E11*V11 | X11: =E11*F11 | Y11: =W11-X11 | Z11: =IFERROR(Y11/X11,"") | AA11: =W11/$W$27 | AB11: =IFERROR(IF(N(H11)>0,H11/G11-1,""),"") | AC11: =IFERROR(V11/I11-1,"") | AD11: =IFERROR(V11/J11-1,"") | AE11: =IFERROR(V11/M11-1,"") | AF11: =IF(N(Q11)>0,Q11/V11-1,"") | AG11: =IF(N(Q11)>0,Q11*Inputs!$B$7,"") | AH11: =IF(N(Q11)>0,Q11*(1+Inputs!$B$8),"") | AI11: =E11*Inputs!$B$9 | AJ11: =IF(N(AG11)>0,AI11*AG11,"") | AK11: =MAX(K11*(1-Inputs!$B$10),F11*(1-IF(ISNUMBER(SEARCH("Lev",C11)),Inputs!$B$12,Inputs!$B$11))) | AL11: =IFERROR(V11/AK11-1,"") | AM11: =IF(V11>=F11/(1-Inputs!$B$13),MAX(F11,L11*(1-Inputs!$B$13)),"not green yet") | AN11: =IF(AND(N(Q11)>0,V11>AK11,AG11>V11),(AG11-V11)/(V11-AK11),"") | AO11: =IF(W11<100,"DUST: clean up",IF(V11<AK11,"REVIEW: below support / max loss",IF(AND(N(Q11)>0,V11>=AH11),"SELL 2nd TRIM, trail the rest",IF(AND(N(Q11)>0,V11>=AG11),"TRIM 1/3 + thesis re-check",IF(AA11>IF(ISNUMBER(SEARCH("Lev",C11)),Inputs!$B$15,Inputs!$B$14),"OVERWEIGHT: trim to cap",IF(IF(ISNUMBER(U11),AND(U11>Inputs!$B$5,U11-Inputs!$B$5<=Inputs!$B$16),FALSE),"HOLD: earnings soon",IF(N(Q11)=0,"HOLD: no target","HOLD"))))))) | AP11: =IFERROR(INDEX('Rank Calc'!$P$5:$P$53,MATCH($A11,'Rank Calc'!$A$5:$A$53,0)),"") | AQ11: Q3 EPS 8.19 vs 7.56 est (beat).
A12: CDNS | B12: Cadence Design | C12: Stock | D12: EDA software | E12: 20 | F12: 316.43 | G12: 342.75 | H12: 337.94 | I12: 320.24 | J12: 327.46 | K12: 273.07 | L12: 361.91 | M12: 416.69 | N12: 593.26 | O12: 415.04 | Q12: 504.15 | R12: LOW | S12: FAIR -9% (high) | T12: INNOVATING | U12: n/a | V12: =IF(AND(Inputs!$B$6="After-hours",N(H12)>0),H12,G12) | W12: =E12*V12 | X12: =E12*F12 | Y12: =W12-X12 | Z12: =IFERROR(Y12/X12,"") | AA12: =W12/$W$27 | AB12: =IFERROR(IF(N(H12)>0,H12/G12-1,""),"") | AC12: =IFERROR(V12/I12-1,"") | AD12: =IFERROR(V12/J12-1,"") | AE12: =IFERROR(V12/M12-1,"") | AF12: =IF(N(Q12)>0,Q12/V12-1,"") | AG12: =IF(N(Q12)>0,Q12*Inputs!$B$7,"") | AH12: =IF(N(Q12)>0,Q12*(1+Inputs!$B$8),"") | AI12: =E12*Inputs!$B$9 | AJ12: =IF(N(AG12)>0,AI12*AG12,"") | AK12: =MAX(K12*(1-Inputs!$B$10),F12*(1-IF(ISNUMBER(SEARCH("Lev",C12)),Inputs!$B$12,Inputs!$B$11))) | AL12: =IFERROR(V12/AK12-1,"") | AM12: =IF(V12>=F12/(1-Inputs!$B$13),MAX(F12,L12*(1-Inputs!$B$13)),"not green yet") | AN12: =IF(AND(N(Q12)>0,V12>AK12,AG12>V12),(AG12-V12)/(V12-AK12),"") | AO12: =IF(W12<100,"DUST: clean up",IF(V12<AK12,"REVIEW: below support / max loss",IF(AND(N(Q12)>0,V12>=AH12),"SELL 2nd TRIM, trail the rest",IF(AND(N(Q12)>0,V12>=AG12),"TRIM 1/3 + thesis re-check",IF(AA12>IF(ISNUMBER(SEARCH("Lev",C12)),Inputs!$B$15,Inputs!$B$14),"OVERWEIGHT: trim to cap",IF(IF(ISNUMBER(U12),AND(U12>Inputs!$B$5,U12-Inputs!$B$5<=Inputs!$B$16),FALSE),"HOLD: earnings soon",IF(N(Q12)=0,"HOLD: no target","HOLD"))))))) | AP12: =IFERROR(INDEX('Rank Calc'!$P$5:$P$53,MATCH($A12,'Rank Calc'!$A$5:$A$53,0)),"") | AQ12: Target agreement LOW: fundamental and Robinhood targets 35% apart.
A13: NOW | B13: ServiceNow | C13: Stock | D13: Software | E13: 46.881838 | F13: 103.9 | G13: 109.67 | H13: 109.23 | I13: 139.99 | J13: 115.34 | K13: 111.8 | L13: 159.5 | M13: 192.97 | O13: 158.78 | P13: 195.5 | Q13: 177.14 | R13: MED | S13: DEEP VALUE +92% (low) | T13: DISRUPTOR | U13: n/a | V13: =IF(AND(Inputs!$B$6="After-hours",N(H13)>0),H13,G13) | W13: =E13*V13 | X13: =E13*F13 | Y13: =W13-X13 | Z13: =IFERROR(Y13/X13,"") | AA13: =W13/$W$27 | AB13: =IFERROR(IF(N(H13)>0,H13/G13-1,""),"") | AC13: =IFERROR(V13/I13-1,"") | AD13: =IFERROR(V13/J13-1,"") | AE13: =IFERROR(V13/M13-1,"") | AF13: =IF(N(Q13)>0,Q13/V13-1,"") | AG13: =IF(N(Q13)>0,Q13*Inputs!$B$7,"") | AH13: =IF(N(Q13)>0,Q13*(1+Inputs!$B$8),"") | AI13: =E13*Inputs!$B$9 | AJ13: =IF(N(AG13)>0,AI13*AG13,"") | AK13: =MAX(K13*(1-Inputs!$B$10),F13*(1-IF(ISNUMBER(SEARCH("Lev",C13)),Inputs!$B$12,Inputs!$B$11))) | AL13: =IFERROR(V13/AK13-1,"") | AM13: =IF(V13>=F13/(1-Inputs!$B$13),MAX(F13,L13*(1-Inputs!$B$13)),"not green yet") | AN13: =IF(AND(N(Q13)>0,V13>AK13,AG13>V13),(AG13-V13)/(V13-AK13),"") | AO13: =IF(W13<100,"DUST: clean up",IF(V13<AK13,"REVIEW: below support / max loss",IF(AND(N(Q13)>0,V13>=AH13),"SELL 2nd TRIM, trail the rest",IF(AND(N(Q13)>0,V13>=AG13),"TRIM 1/3 + thesis re-check",IF(AA13>IF(ISNUMBER(SEARCH("Lev",C13)),Inputs!$B$15,Inputs!$B$14),"OVERWEIGHT: trim to cap",IF(IF(ISNUMBER(U13),AND(U13>Inputs!$B$5,U13-Inputs!$B$5<=Inputs!$B$16),FALSE),"HOLD: earnings soon",IF(N(Q13)=0,"HOLD: no target","HOLD"))))))) | AP13: =IFERROR(INDEX('Rank Calc'!$P$5:$P$53,MATCH($A13,'Rank Calc'!$A$5:$A$53,0)),"") | AQ13: Closed below its 60-day low on 10/29.
A14: ASND | B14: Ascendis Pharma | C14: Stock | D14: Biotech | E14: 20 | F14: 226.14 | G14: 253 | H14: 253 | I14: 242.38 | J14: 237.93 | K14: 219.52 | L14: 272.47 | M14: 282.15 | O14: 302.81 | P14: 302 | Q14: 302.4 | R14: MED | S14: n/a | T14: DISRUPTOR | U14: 46337 | V14: =IF(AND(Inputs!$B$6="After-hours",N(H14)>0),H14,G14) | W14: =E14*V14 | X14: =E14*F14 | Y14: =W14-X14 | Z14: =IFERROR(Y14/X14,"") | AA14: =W14/$W$27 | AB14: =IFERROR(IF(N(H14)>0,H14/G14-1,""),"") | AC14: =IFERROR(V14/I14-1,"") | AD14: =IFERROR(V14/J14-1,"") | AE14: =IFERROR(V14/M14-1,"") | AF14: =IF(N(Q14)>0,Q14/V14-1,"") | AG14: =IF(N(Q14)>0,Q14*Inputs!$B$7,"") | AH14: =IF(N(Q14)>0,Q14*(1+Inputs!$B$8),"") | AI14: =E14*Inputs!$B$9 | AJ14: =IF(N(AG14)>0,AI14*AG14,"") | AK14: =MAX(K14*(1-Inputs!$B$10),F14*(1-IF(ISNUMBER(SEARCH("Lev",C14)),Inputs!$B$12,Inputs!$B$11))) | AL14: =IFERROR(V14/AK14-1,"") | AM14: =IF(V14>=F14/(1-Inputs!$B$13),MAX(F14,L14*(1-Inputs!$B$13)),"not green yet") | AN14: =IF(AND(N(Q14)>0,V14>AK14,AG14>V14),(AG14-V14)/(V14-AK14),"") | AO14: =IF(W14<100,"DUST: clean up",IF(V14<AK14,"REVIEW: below support / max loss",IF(AND(N(Q14)>0,V14>=AH14),"SELL 2nd TRIM, trail the rest",IF(AND(N(Q14)>0,V14>=AG14),"TRIM 1/3 + thesis re-check",IF(AA14>IF(ISNUMBER(SEARCH("Lev",C14)),Inputs!$B$15,Inputs!$B$14),"OVERWEIGHT: trim to cap",IF(IF(ISNUMBER(U14),AND(U14>Inputs!$B$5,U14-Inputs!$B$5<=Inputs!$B$16),FALSE),"HOLD: earnings soon",IF(N(Q14)=0,"HOLD: no target","HOLD"))))))) | AP14: =IFERROR(INDEX('Rank Calc'!$P$5:$P$53,MATCH($A14,'Rank Calc'!$A$5:$A$53,0)),"") | AQ14: Earnings date unverified.
A15: VST | B15: Vistra | C15: Stock | D15: Power generation | E15: 35 | F15: 140.54 | G15: 140.95 | H15: 137.85 | I15: 145.12 | J15: 153.77 | K15: 133.44 | L15: 168.75 | M15: 198.82 | N15: 234.71 | O15: 207.86 | P15: 224 | Q15: 224 | R15: HIGH | S15: EXPENSIVE -35% (low) | T15: STABLE | U15: 46332 | V15: =IF(AND(Inputs!$B$6="After-hours",N(H15)>0),H15,G15) | W15: =E15*V15 | X15: =E15*F15 | Y15: =W15-X15 | Z15: =IFERROR(Y15/X15,"") | AA15: =W15/$W$27 | AB15: =IFERROR(IF(N(H15)>0,H15/G15-1,""),"") | AC15: =IFERROR(V15/I15-1,"") | AD15: =IFERROR(V15/J15-1,"") | AE15: =IFERROR(V15/M15-1,"") | AF15: =IF(N(Q15)>0,Q15/V15-1,"") | AG15: =IF(N(Q15)>0,Q15*Inputs!$B$7,"") | AH15: =IF(N(Q15)>0,Q15*(1+Inputs!$B$8),"") | AI15: =E15*Inputs!$B$9 | AJ15: =IF(N(AG15)>0,AI15*AG15,"") | AK15: =MAX(K15*(1-Inputs!$B$10),F15*(1-IF(ISNUMBER(SEARCH("Lev",C15)),Inputs!$B$12,Inputs!$B$11))) | AL15: =IFERROR(V15/AK15-1,"") | AM15: =IF(V15>=F15/(1-Inputs!$B$13),MAX(F15,L15*(1-Inputs!$B$13)),"not green yet") | AN15: =IF(AND(N(Q15)>0,V15>AK15,AG15>V15),(AG15-V15)/(V15-AK15),"") | AO15: =IF(W15<100,"DUST: clean up",IF(V15<AK15,"REVIEW: below support / max loss",IF(AND(N(Q15)>0,V15>=AH15),"SELL 2nd TRIM, trail the rest",IF(AND(N(Q15)>0,V15>=AG15),"TRIM 1/3 + thesis re-check",IF(AA15>IF(ISNUMBER(SEARCH("Lev",C15)),Inputs!$B$15,Inputs!$B$14),"OVERWEIGHT: trim to cap",IF(IF(ISNUMBER(U15),AND(U15>Inputs!$B$5,U15-Inputs!$B$5<=Inputs!$B$16),FALSE),"HOLD: earnings soon",IF(N(Q15)=0,"HOLD: no target","HOLD"))))))) | AP15: =IFERROR(INDEX('Rank Calc'!$P$5:$P$53,MATCH($A15,'Rank Calc'!$A$5:$A$53,0)),"")
A16: CRDO | B16: Credo Technology | C16: Stock | D16: Semiconductors | E16: 25 | F16: 164.53 | G16: 165.29 | H16: 155.65 | I16: 190.17 | J16: 181.14 | K16: 142.89 | L16: 286.24 | M16: 308.67 | N16: 189.97 | O16: 281.59 | P16: 292 | Q16: 281.59 | R16: LOW | S16: EXPENSIVE -31% (low) | T16: DISRUPTOR | U16: n/a | V16: =IF(AND(Inputs!$B$6="After-hours",N(H16)>0),H16,G16) | W16: =E16*V16 | X16: =E16*F16 | Y16: =W16-X16 | Z16: =IFERROR(Y16/X16,"") | AA16: =W16/$W$27 | AB16: =IFERROR(IF(N(H16)>0,H16/G16-1,""),"") | AC16: =IFERROR(V16/I16-1,"") | AD16: =IFERROR(V16/J16-1,"") | AE16: =IFERROR(V16/M16-1,"") | AF16: =IF(N(Q16)>0,Q16/V16-1,"") | AG16: =IF(N(Q16)>0,Q16*Inputs!$B$7,"") | AH16: =IF(N(Q16)>0,Q16*(1+Inputs!$B$8),"") | AI16: =E16*Inputs!$B$9 | AJ16: =IF(N(AG16)>0,AI16*AG16,"") | AK16: =MAX(K16*(1-Inputs!$B$10),F16*(1-IF(ISNUMBER(SEARCH("Lev",C16)),Inputs!$B$12,Inputs!$B$11))) | AL16: =IFERROR(V16/AK16-1,"") | AM16: =IF(V16>=F16/(1-Inputs!$B$13),MAX(F16,L16*(1-Inputs!$B$13)),"not green yet") | AN16: =IF(AND(N(Q16)>0,V16>AK16,AG16>V16),(AG16-V16)/(V16-AK16),"") | AO16: =IF(W16<100,"DUST: clean up",IF(V16<AK16,"REVIEW: below support / max loss",IF(AND(N(Q16)>0,V16>=AH16),"SELL 2nd TRIM, trail the rest",IF(AND(N(Q16)>0,V16>=AG16),"TRIM 1/3 + thesis re-check",IF(AA16>IF(ISNUMBER(SEARCH("Lev",C16)),Inputs!$B$15,Inputs!$B$14),"OVERWEIGHT: trim to cap",IF(IF(ISNUMBER(U16),AND(U16>Inputs!$B$5,U16-Inputs!$B$5<=Inputs!$B$16),FALSE),"HOLD: earnings soon",IF(N(Q16)=0,"HOLD: no target","HOLD"))))))) | AP16: =IFERROR(INDEX('Rank Calc'!$P$5:$P$53,MATCH($A16,'Rank Calc'!$A$5:$A$53,0)),"") | AQ16: -5.8% after hours.
A17: SNDK | B17: Sandisk | C17: Stock | D17: Memory | E17: 3 | F17: 1278.16 | G17: 1330.05 | H17: 1309.34 | I17: 1568.4 | J17: 1255.73 | K17: 1163.09 | L17: 1909.48 | M17: 2354.39 | O17: 2287.38 | P17: 1737.5 | Q17: 2012.44 | R17: MED | S17: EXPENSIVE -50% (low) | T17: INNOVATING | U17: 46324 | V17: =IF(AND(Inputs!$B$6="After-hours",N(H17)>0),H17,G17) | W17: =E17*V17 | X17: =E17*F17 | Y17: =W17-X17 | Z17: =IFERROR(Y17/X17,"") | AA17: =W17/$W$27 | AB17: =IFERROR(IF(N(H17)>0,H17/G17-1,""),"") | AC17: =IFERROR(V17/I17-1,"") | AD17: =IFERROR(V17/J17-1,"") | AE17: =IFERROR(V17/M17-1,"") | AF17: =IF(N(Q17)>0,Q17/V17-1,"") | AG17: =IF(N(Q17)>0,Q17*Inputs!$B$7,"") | AH17: =IF(N(Q17)>0,Q17*(1+Inputs!$B$8),"") | AI17: =E17*Inputs!$B$9 | AJ17: =IF(N(AG17)>0,AI17*AG17,"") | AK17: =MAX(K17*(1-Inputs!$B$10),F17*(1-IF(ISNUMBER(SEARCH("Lev",C17)),Inputs!$B$12,Inputs!$B$11))) | AL17: =IFERROR(V17/AK17-1,"") | AM17: =IF(V17>=F17/(1-Inputs!$B$13),MAX(F17,L17*(1-Inputs!$B$13)),"not green yet") | AN17: =IF(AND(N(Q17)>0,V17>AK17,AG17>V17),(AG17-V17)/(V17-AK17),"") | AO17: =IF(W17<100,"DUST: clean up",IF(V17<AK17,"REVIEW: below support / max loss",IF(AND(N(Q17)>0,V17>=AH17),"SELL 2nd TRIM, trail the rest",IF(AND(N(Q17)>0,V17>=AG17),"TRIM 1/3 + thesis re-check",IF(AA17>IF(ISNUMBER(SEARCH("Lev",C17)),Inputs!$B$15,Inputs!$B$14),"OVERWEIGHT: trim to cap",IF(IF(ISNUMBER(U17),AND(U17>Inputs!$B$5,U17-Inputs!$B$5<=Inputs!$B$16),FALSE),"HOLD: earnings soon",IF(N(Q17)=0,"HOLD: no target","HOLD"))))))) | AP17: =IFERROR(INDEX('Rank Calc'!$P$5:$P$53,MATCH($A17,'Rank Calc'!$A$5:$A$53,0)),"") | AQ17: FQ1 EPS 49.51 vs 46.36 est (beat).
A18: OKLO | B18: Oklo | C18: Stock | D18: Nuclear (pre-revenue) | E18: 100 | F18: 26.73 | G18: 26.81 | H18: 25.78 | I18: 35.86 | J18: 54.21 | K18: 25.39 | L18: 49.48 | M18: 145.3 | O18: 62.83 | P18: 37 | Q18: 49.91 | R18: LOW | S18: n/a | T18: N/A | U18: 46332 | V18: =IF(AND(Inputs!$B$6="After-hours",N(H18)>0),H18,G18) | W18: =E18*V18 | X18: =E18*F18 | Y18: =W18-X18 | Z18: =IFERROR(Y18/X18,"") | AA18: =W18/$W$27 | AB18: =IFERROR(IF(N(H18)>0,H18/G18-1,""),"") | AC18: =IFERROR(V18/I18-1,"") | AD18: =IFERROR(V18/J18-1,"") | AE18: =IFERROR(V18/M18-1,"") | AF18: =IF(N(Q18)>0,Q18/V18-1,"") | AG18: =IF(N(Q18)>0,Q18*Inputs!$B$7,"") | AH18: =IF(N(Q18)>0,Q18*(1+Inputs!$B$8),"") | AI18: =E18*Inputs!$B$9 | AJ18: =IF(N(AG18)>0,AI18*AG18,"") | AK18: =MAX(K18*(1-Inputs!$B$10),F18*(1-IF(ISNUMBER(SEARCH("Lev",C18)),Inputs!$B$12,Inputs!$B$11))) | AL18: =IFERROR(V18/AK18-1,"") | AM18: =IF(V18>=F18/(1-Inputs!$B$13),MAX(F18,L18*(1-Inputs!$B$13)),"not green yet") | AN18: =IF(AND(N(Q18)>0,V18>AK18,AG18>V18),(AG18-V18)/(V18-AK18),"") | AO18: =IF(W18<100,"DUST: clean up",IF(V18<AK18,"REVIEW: below support / max loss",IF(AND(N(Q18)>0,V18>=AH18),"SELL 2nd TRIM, trail the rest",IF(AND(N(Q18)>0,V18>=AG18),"TRIM 1/3 + thesis re-check",IF(AA18>IF(ISNUMBER(SEARCH("Lev",C18)),Inputs!$B$15,Inputs!$B$14),"OVERWEIGHT: trim to cap",IF(IF(ISNUMBER(U18),AND(U18>Inputs!$B$5,U18-Inputs!$B$5<=Inputs!$B$16),FALSE),"HOLD: earnings soon",IF(N(Q18)=0,"HOLD: no target","HOLD"))))))) | AP18: =IFERROR(INDEX('Rank Calc'!$P$5:$P$53,MATCH($A18,'Rank Calc'!$A$5:$A$53,0)),"") | AQ18: At 52-week low. Targets disagree (52% spread).
A19: AAOX | B19: AAOI 2x Leveraged ETF | C19: 2x Lev ETF | D19: Optical networking | E19: 500 | F19: 3.84 | G19: 5.1 | H19: 4.49 | I19: 9.57 | J19: 28.89 | K19: 3.6 | L19: 27.57 | M19: 103 | Q19: 9.57 | R19: TECH (50-day) | S19: n/a | T19: N/A | U19: n/a | V19: =IF(AND(Inputs!$B$6="After-hours",N(H19)>0),H19,G19) | W19: =E19*V19 | X19: =E19*F19 | Y19: =W19-X19 | Z19: =IFERROR(Y19/X19,"") | AA19: =W19/$W$27 | AB19: =IFERROR(IF(N(H19)>0,H19/G19-1,""),"") | AC19: =IFERROR(V19/I19-1,"") | AD19: =IFERROR(V19/J19-1,"") | AE19: =IFERROR(V19/M19-1,"") | AF19: =IF(N(Q19)>0,Q19/V19-1,"") | AG19: =IF(N(Q19)>0,Q19*Inputs!$B$7,"") | AH19: =IF(N(Q19)>0,Q19*(1+Inputs!$B$8),"") | AI19: =E19*Inputs!$B$9 | AJ19: =IF(N(AG19)>0,AI19*AG19,"") | AK19: =MAX(K19*(1-Inputs!$B$10),F19*(1-IF(ISNUMBER(SEARCH("Lev",C19)),Inputs!$B$12,Inputs!$B$11))) | AL19: =IFERROR(V19/AK19-1,"") | AM19: =IF(V19>=F19/(1-Inputs!$B$13),MAX(F19,L19*(1-Inputs!$B$13)),"not green yet") | AN19: =IF(AND(N(Q19)>0,V19>AK19,AG19>V19),(AG19-V19)/(V19-AK19),"") | AO19: =IF(W19<100,"DUST: clean up",IF(V19<AK19,"REVIEW: below support / max loss",IF(AND(N(Q19)>0,V19>=AH19),"SELL 2nd TRIM, trail the rest",IF(AND(N(Q19)>0,V19>=AG19),"TRIM 1/3 + thesis re-check",IF(AA19>IF(ISNUMBER(SEARCH("Lev",C19)),Inputs!$B$15,Inputs!$B$14),"OVERWEIGHT: trim to cap",IF(IF(ISNUMBER(U19),AND(U19>Inputs!$B$5,U19-Inputs!$B$5<=Inputs!$B$16),FALSE),"HOLD: earnings soon",IF(N(Q19)=0,"HOLD: no target","HOLD"))))))) | AP19: =IFERROR(INDEX('Rank Calc'!$P$5:$P$53,MATCH($A19,'Rank Calc'!$A$5:$A$53,0)),"") | AQ19: 2x daily leverage on one stock; -95% from 52-wk high. Target = 50-day SMA.
A20: GOOGL | B20: Alphabet | C20: Stock | D20: Internet | E20: 6.848872 | F20: 297.58 | G20: 283.82 | H20: 282.23 | I20: 341.11 | J20: 341.14 | K20: 316.6 | L20: 364.17 | M20: 408.61 | N20: 367.54 | O20: 405.31 | P20: 425 | Q20: 405.31 | R20: HIGH | S20: RICH -12% (low) | T20: DISRUPTOR | U20: n/a | V20: =IF(AND(Inputs!$B$6="After-hours",N(H20)>0),H20,G20) | W20: =E20*V20 | X20: =E20*F20 | Y20: =W20-X20 | Z20: =IFERROR(Y20/X20,"") | AA20: =W20/$W$27 | AB20: =IFERROR(IF(N(H20)>0,H20/G20-1,""),"") | AC20: =IFERROR(V20/I20-1,"") | AD20: =IFERROR(V20/J20-1,"") | AE20: =IFERROR(V20/M20-1,"") | AF20: =IF(N(Q20)>0,Q20/V20-1,"") | AG20: =IF(N(Q20)>0,Q20*Inputs!$B$7,"") | AH20: =IF(N(Q20)>0,Q20*(1+Inputs!$B$8),"") | AI20: =E20*Inputs!$B$9 | AJ20: =IF(N(AG20)>0,AI20*AG20,"") | AK20: =MAX(K20*(1-Inputs!$B$10),F20*(1-IF(ISNUMBER(SEARCH("Lev",C20)),Inputs!$B$12,Inputs!$B$11))) | AL20: =IFERROR(V20/AK20-1,"") | AM20: =IF(V20>=F20/(1-Inputs!$B$13),MAX(F20,L20*(1-Inputs!$B$13)),"not green yet") | AN20: =IF(AND(N(Q20)>0,V20>AK20,AG20>V20),(AG20-V20)/(V20-AK20),"") | AO20: =IF(W20<100,"DUST: clean up",IF(V20<AK20,"REVIEW: below support / max loss",IF(AND(N(Q20)>0,V20>=AH20),"SELL 2nd TRIM, trail the rest",IF(AND(N(Q20)>0,V20>=AG20),"TRIM 1/3 + thesis re-check",IF(AA20>IF(ISNUMBER(SEARCH("Lev",C20)),Inputs!$B$15,Inputs!$B$14),"OVERWEIGHT: trim to cap",IF(IF(ISNUMBER(U20),AND(U20>Inputs!$B$5,U20-Inputs!$B$5<=Inputs!$B$16),FALSE),"HOLD: earnings soon",IF(N(Q20)=0,"HOLD: no target","HOLD"))))))) | AP20: =IFERROR(INDEX('Rank Calc'!$P$5:$P$53,MATCH($A20,'Rank Calc'!$A$5:$A$53,0)),"") | AQ20: Well below 60-day low and both moving averages.
A21: IONQ | B21: IonQ | C21: Stock | D21: Quantum computing | E21: 30 | F21: 33.21 | G21: 31.72 | H21: 30.81 | I21: 38.44 | J21: 42.15 | K21: 29.94 | L21: 47.95 | M21: 73.65 | O21: 65.77 | Q21: 65.77 | R21: LOW | S21: n/a | T21: AT RISK | U21: 46331 | V21: =IF(AND(Inputs!$B$6="After-hours",N(H21)>0),H21,G21) | W21: =E21*V21 | X21: =E21*F21 | Y21: =W21-X21 | Z21: =IFERROR(Y21/X21,"") | AA21: =W21/$W$27 | AB21: =IFERROR(IF(N(H21)>0,H21/G21-1,""),"") | AC21: =IFERROR(V21/I21-1,"") | AD21: =IFERROR(V21/J21-1,"") | AE21: =IFERROR(V21/M21-1,"") | AF21: =IF(N(Q21)>0,Q21/V21-1,"") | AG21: =IF(N(Q21)>0,Q21*Inputs!$B$7,"") | AH21: =IF(N(Q21)>0,Q21*(1+Inputs!$B$8),"") | AI21: =E21*Inputs!$B$9 | AJ21: =IF(N(AG21)>0,AI21*AG21,"") | AK21: =MAX(K21*(1-Inputs!$B$10),F21*(1-IF(ISNUMBER(SEARCH("Lev",C21)),Inputs!$B$12,Inputs!$B$11))) | AL21: =IFERROR(V21/AK21-1,"") | AM21: =IF(V21>=F21/(1-Inputs!$B$13),MAX(F21,L21*(1-Inputs!$B$13)),"not green yet") | AN21: =IF(AND(N(Q21)>0,V21>AK21,AG21>V21),(AG21-V21)/(V21-AK21),"") | AO21: =IF(W21<100,"DUST: clean up",IF(V21<AK21,"REVIEW: below support / max loss",IF(AND(N(Q21)>0,V21>=AH21),"SELL 2nd TRIM, trail the rest",IF(AND(N(Q21)>0,V21>=AG21),"TRIM 1/3 + thesis re-check",IF(AA21>IF(ISNUMBER(SEARCH("Lev",C21)),Inputs!$B$15,Inputs!$B$14),"OVERWEIGHT: trim to cap",IF(IF(ISNUMBER(U21),AND(U21>Inputs!$B$5,U21-Inputs!$B$5<=Inputs!$B$16),FALSE),"HOLD: earnings soon",IF(N(Q21)=0,"HOLD: no target","HOLD"))))))) | AP21: =IFERROR(INDEX('Rank Calc'!$P$5:$P$53,MATCH($A21,'Rank Calc'!$A$5:$A$53,0)),"") | AQ21: Only one target method available.
A22: AUR | B22: Aurora Innovation | C22: Stock | D22: Autonomous trucking | E22: 200 | F22: 4.91 | G22: 4.405 | H22: 4.37 | I22: 5.73 | J22: 5.63 | K22: 4.4 | L22: 7.16 | M22: 8.57 | O22: 11.33 | P22: 12.5 | Q22: 11.91 | R22: MED | S22: n/a | T22: INNOVATING | U22: n/a | V22: =IF(AND(Inputs!$B$6="After-hours",N(H22)>0),H22,G22) | W22: =E22*V22 | X22: =E22*F22 | Y22: =W22-X22 | Z22: =IFERROR(Y22/X22,"") | AA22: =W22/$W$27 | AB22: =IFERROR(IF(N(H22)>0,H22/G22-1,""),"") | AC22: =IFERROR(V22/I22-1,"") | AD22: =IFERROR(V22/J22-1,"") | AE22: =IFERROR(V22/M22-1,"") | AF22: =IF(N(Q22)>0,Q22/V22-1,"") | AG22: =IF(N(Q22)>0,Q22*Inputs!$B$7,"") | AH22: =IF(N(Q22)>0,Q22*(1+Inputs!$B$8),"") | AI22: =E22*Inputs!$B$9 | AJ22: =IF(N(AG22)>0,AI22*AG22,"") | AK22: =MAX(K22*(1-Inputs!$B$10),F22*(1-IF(ISNUMBER(SEARCH("Lev",C22)),Inputs!$B$12,Inputs!$B$11))) | AL22: =IFERROR(V22/AK22-1,"") | AM22: =IF(V22>=F22/(1-Inputs!$B$13),MAX(F22,L22*(1-Inputs!$B$13)),"not green yet") | AN22: =IF(AND(N(Q22)>0,V22>AK22,AG22>V22),(AG22-V22)/(V22-AK22),"") | AO22: =IF(W22<100,"DUST: clean up",IF(V22<AK22,"REVIEW: below support / max loss",IF(AND(N(Q22)>0,V22>=AH22),"SELL 2nd TRIM, trail the rest",IF(AND(N(Q22)>0,V22>=AG22),"TRIM 1/3 + thesis re-check",IF(AA22>IF(ISNUMBER(SEARCH("Lev",C22)),Inputs!$B$15,Inputs!$B$14),"OVERWEIGHT: trim to cap",IF(IF(ISNUMBER(U22),AND(U22>Inputs!$B$5,U22-Inputs!$B$5<=Inputs!$B$16),FALSE),"HOLD: earnings soon",IF(N(Q22)=0,"HOLD: no target","HOLD"))))))) | AP22: =IFERROR(INDEX('Rank Calc'!$P$5:$P$53,MATCH($A22,'Rank Calc'!$A$5:$A$53,0)),"") | AQ22: Sitting on its 60-day low.
A23: QQQI | B23: NEOS Nasdaq-100 Income | C23: ETF | D23: Nasdaq-100 covered call | E23: 0.567476 | F23: 53.83 | G23: 53.42 | H23: 52.61 | I23: 54.72 | J23: 54.18 | K23: 52.36 | L23: 56.84 | M23: 57.84 | R23: n/a | S23: n/a | T23: N/A | U23: n/a | V23: =IF(AND(Inputs!$B$6="After-hours",N(H23)>0),H23,G23) | W23: =E23*V23 | X23: =E23*F23 | Y23: =W23-X23 | Z23: =IFERROR(Y23/X23,"") | AA23: =W23/$W$27 | AB23: =IFERROR(IF(N(H23)>0,H23/G23-1,""),"") | AC23: =IFERROR(V23/I23-1,"") | AD23: =IFERROR(V23/J23-1,"") | AE23: =IFERROR(V23/M23-1,"") | AF23: =IF(N(Q23)>0,Q23/V23-1,"") | AG23: =IF(N(Q23)>0,Q23*Inputs!$B$7,"") | AH23: =IF(N(Q23)>0,Q23*(1+Inputs!$B$8),"") | AI23: =E23*Inputs!$B$9 | AJ23: =IF(N(AG23)>0,AI23*AG23,"") | AK23: =MAX(K23*(1-Inputs!$B$10),F23*(1-IF(ISNUMBER(SEARCH("Lev",C23)),Inputs!$B$12,Inputs!$B$11))) | AL23: =IFERROR(V23/AK23-1,"") | AM23: =IF(V23>=F23/(1-Inputs!$B$13),MAX(F23,L23*(1-Inputs!$B$13)),"not green yet") | AN23: =IF(AND(N(Q23)>0,V23>AK23,AG23>V23),(AG23-V23)/(V23-AK23),"") | AO23: =IF(W23<100,"DUST: clean up",IF(V23<AK23,"REVIEW: below support / max loss",IF(AND(N(Q23)>0,V23>=AH23),"SELL 2nd TRIM, trail the rest",IF(AND(N(Q23)>0,V23>=AG23),"TRIM 1/3 + thesis re-check",IF(AA23>IF(ISNUMBER(SEARCH("Lev",C23)),Inputs!$B$15,Inputs!$B$14),"OVERWEIGHT: trim to cap",IF(IF(ISNUMBER(U23),AND(U23>Inputs!$B$5,U23-Inputs!$B$5<=Inputs!$B$16),FALSE),"HOLD: earnings soon",IF(N(Q23)=0,"HOLD: no target","HOLD"))))))) | AP23: =IFERROR(INDEX('Rank Calc'!$P$5:$P$53,MATCH($A23,'Rank Calc'!$A$5:$A$53,0)),"") | AQ23: Fractional leftover (~$30).
A24: QQQ | B24: Invesco QQQ | C24: ETF | D24: Nasdaq-100 | E24: 0.04204 | F24: 713.61 | G24: 715.34 | H24: 702.61 | I24: 725.61 | J24: 679.22 | K24: 700 | L24: 762.86 | M24: 762.86 | R24: n/a | S24: n/a | T24: N/A | U24: n/a | V24: =IF(AND(Inputs!$B$6="After-hours",N(H24)>0),H24,G24) | W24: =E24*V24 | X24: =E24*F24 | Y24: =W24-X24 | Z24: =IFERROR(Y24/X24,"") | AA24: =W24/$W$27 | AB24: =IFERROR(IF(N(H24)>0,H24/G24-1,""),"") | AC24: =IFERROR(V24/I24-1,"") | AD24: =IFERROR(V24/J24-1,"") | AE24: =IFERROR(V24/M24-1,"") | AF24: =IF(N(Q24)>0,Q24/V24-1,"") | AG24: =IF(N(Q24)>0,Q24*Inputs!$B$7,"") | AH24: =IF(N(Q24)>0,Q24*(1+Inputs!$B$8),"") | AI24: =E24*Inputs!$B$9 | AJ24: =IF(N(AG24)>0,AI24*AG24,"") | AK24: =MAX(K24*(1-Inputs!$B$10),F24*(1-IF(ISNUMBER(SEARCH("Lev",C24)),Inputs!$B$12,Inputs!$B$11))) | AL24: =IFERROR(V24/AK24-1,"") | AM24: =IF(V24>=F24/(1-Inputs!$B$13),MAX(F24,L24*(1-Inputs!$B$13)),"not green yet") | AN24: =IF(AND(N(Q24)>0,V24>AK24,AG24>V24),(AG24-V24)/(V24-AK24),"") | AO24: =IF(W24<100,"DUST: clean up",IF(V24<AK24,"REVIEW: below support / max loss",IF(AND(N(Q24)>0,V24>=AH24),"SELL 2nd TRIM, trail the rest",IF(AND(N(Q24)>0,V24>=AG24),"TRIM 1/3 + thesis re-check",IF(AA24>IF(ISNUMBER(SEARCH("Lev",C24)),Inputs!$B$15,Inputs!$B$14),"OVERWEIGHT: trim to cap",IF(IF(ISNUMBER(U24),AND(U24>Inputs!$B$5,U24-Inputs!$B$5<=Inputs!$B$16),FALSE),"HOLD: earnings soon",IF(N(Q24)=0,"HOLD: no target","HOLD"))))))) | AP24: =IFERROR(INDEX('Rank Calc'!$P$5:$P$53,MATCH($A24,'Rank Calc'!$A$5:$A$53,0)),"") | AQ24: Fractional leftover (~$30).
A25: HOOD | B25: Robinhood Markets | C25: Stock | D25: Brokerage | E25: 0.010482 | F25: 90.63 | G25: 91.59 | H25: 87.37 | I25: 108.69 | J25: 92.76 | K25: 89.15 | L25: 126.74 | M25: 150.47 | O25: 133.63 | P25: 145 | Q25: 139.31 | R25: MED | S25: n/a | T25: DISRUPTOR | U25: n/a | V25: =IF(AND(Inputs!$B$6="After-hours",N(H25)>0),H25,G25) | W25: =E25*V25 | X25: =E25*F25 | Y25: =W25-X25 | Z25: =IFERROR(Y25/X25,"") | AA25: =W25/$W$27 | AB25: =IFERROR(IF(N(H25)>0,H25/G25-1,""),"") | AC25: =IFERROR(V25/I25-1,"") | AD25: =IFERROR(V25/J25-1,"") | AE25: =IFERROR(V25/M25-1,"") | AF25: =IF(N(Q25)>0,Q25/V25-1,"") | AG25: =IF(N(Q25)>0,Q25*Inputs!$B$7,"") | AH25: =IF(N(Q25)>0,Q25*(1+Inputs!$B$8),"") | AI25: =E25*Inputs!$B$9 | AJ25: =IF(N(AG25)>0,AI25*AG25,"") | AK25: =MAX(K25*(1-Inputs!$B$10),F25*(1-IF(ISNUMBER(SEARCH("Lev",C25)),Inputs!$B$12,Inputs!$B$11))) | AL25: =IFERROR(V25/AK25-1,"") | AM25: =IF(V25>=F25/(1-Inputs!$B$13),MAX(F25,L25*(1-Inputs!$B$13)),"not green yet") | AN25: =IF(AND(N(Q25)>0,V25>AK25,AG25>V25),(AG25-V25)/(V25-AK25),"") | AO25: =IF(W25<100,"DUST: clean up",IF(V25<AK25,"REVIEW: below support / max loss",IF(AND(N(Q25)>0,V25>=AH25),"SELL 2nd TRIM, trail the rest",IF(AND(N(Q25)>0,V25>=AG25),"TRIM 1/3 + thesis re-check",IF(AA25>IF(ISNUMBER(SEARCH("Lev",C25)),Inputs!$B$15,Inputs!$B$14),"OVERWEIGHT: trim to cap",IF(IF(ISNUMBER(U25),AND(U25>Inputs!$B$5,U25-Inputs!$B$5<=Inputs!$B$16),FALSE),"HOLD: earnings soon",IF(N(Q25)=0,"HOLD: no target","HOLD"))))))) | AP25: =IFERROR(INDEX('Rank Calc'!$P$5:$P$53,MATCH($A25,'Rank Calc'!$A$5:$A$53,0)),"") | AQ25: Fractional leftover (<$1).
A27: TOTAL | W27: =SUM(W6:W25) | X27: =SUM(X6:X25) | Y27: =SUM(Y6:Y25) | Z27: =Y27/X27 | AA27: =SUM(AA6:AA25) | AF27: =SUMPRODUCT(--(Q6:Q25>0),E6:E25,Q6:Q25)/SUMPRODUCT(--(Q6:Q25>0),W6:W25)-1 | AJ27: =SUM(AJ6:AJ25) | AO27: =COUNTIF(AO6:AO25,"REVIEW*")&" review, "&COUNTIF(AO6:AO25,"OVERWEIGHT*")&" overweight, "&COUNTIF(AO6:AO25,"TRIM*")&" trim"

Sheet Watchlist
A1: Joint Watchlist - Quality @ 200-day Buy Zone, Re-buy Watch, New Industries
A2: Ordered by pre-breakout chart setup (most pulled back first). Blue = inputs (10/29 close), green headers = formulas. A status is a prompt to research, never a buy order.
A4: Symbol | B4: Company | C4: List | D4: Held? | E4: Quality Grade | F4: Quality Rank | G4: Chart Setup | H4: Valuation | I4: Disruption | J4: Price | K4: 50-day SMA | L4: 200-day SMA | M4: Analyst Mean Target | N4: # Buy | O4: # Hold | P4: # Sell | Q4: Next Earnings | R4: Wash-Sale Clear | S4: vs 200-day | T4: vs 50-day | U4: Buy Zone Low | V4: Buy Zone High | W4: BUY TARGET | X4: Distance to Buy Target | Y4: Upside: Buy Tgt to Analyst | Z4: WATCH REVIEW LEVEL | AA4: Reward : Risk at Buy Tgt | AB4: % Buy Ratings | AC4: STATUS | AD4: RANK | AE4: Notes
A5: AEM | B5: Agnico Eagle Mines | C5: Buy Zone | E5: A+ | F5: 3 | G5: 86 COILED | H5: RICH -15% (low) | I5: STABLE | J5: 175.92 | K5: 193.8 | L5: 189.53 | M5: 225.4 | N5: 19 | O5: 4 | P5: 1 | Q5: n/a | S5: =J5/L5-1 | T5: =J5/K5-1 | U5: =L5*(1+Inputs!$B$17) | V5: =L5*(1+Inputs!$B$18) | W5: =L5*(1+Inputs!$B$19) | X5: =J5/W5-1 | Y5: =IF(N(M5)>0,M5/W5-1,"") | Z5: =U5 | AA5: =IFERROR(IF(N(M5)>W5,(M5-W5)/(W5-Z5),""),"") | AB5: =IFERROR(N5/(N5+O5+P5),"") | AC5: =IF(D5="HELD","HELD: see Holdings sheet",IF(IF(ISNUMBER(R5),Inputs!$B$5<R5,FALSE),"WASH-SALE LOCK until "&TEXT(R5,"m/d"),IF(J5<U5,"BELOW ZONE: wait for 200-day reclaim",IF(J5>V5,"ABOVE ZONE: extended, wait",IF(IF(ISNUMBER(Q5),AND(Q5>Inputs!$B$5,Q5-Inputs!$B$5<=Inputs!$B$16),FALSE),"IN ZONE: earnings soon, wait",IF(N(M5)<=J5,"IN ZONE: analysts see no upside",IF(J5<=W5,"IN ZONE: at/below buy target - research","IN ZONE: research"))))))) | AD5: =IFERROR(INDEX('Rank Calc'!$P$5:$P$53,MATCH($A5,'Rank Calc'!$A$5:$A$53,0)),"") | AE5: Falling wedge forming; tracks gold.
A6: NVDA | B6: NVIDIA | C6: Buy Zone | E6: A+ | F6: 1 | G6: 71 COILED | H6: FAIR +7% (med) | I6: DISRUPTOR | J6: 213.66 | K6: 221.99 | L6: 204.28 | M6: 334.45 | N6: 69 | O6: 2 | P6: 1 | Q6: 46343 | S6: =J6/L6-1 | T6: =J6/K6-1 | U6: =L6*(1+Inputs!$B$17) | V6: =L6*(1+Inputs!$B$18) | W6: =L6*(1+Inputs!$B$19) | X6: =J6/W6-1 | Y6: =IF(N(M6)>0,M6/W6-1,"") | Z6: =U6 | AA6: =IFERROR(IF(N(M6)>W6,(M6-W6)/(W6-Z6),""),"") | AB6: =IFERROR(N6/(N6+O6+P6),"") | AC6: =IF(D6="HELD","HELD: see Holdings sheet",IF(IF(ISNUMBER(R6),Inputs!$B$5<R6,FALSE),"WASH-SALE LOCK until "&TEXT(R6,"m/d"),IF(J6<U6,"BELOW ZONE: wait for 200-day reclaim",IF(J6>V6,"ABOVE ZONE: extended, wait",IF(IF(ISNUMBER(Q6),AND(Q6>Inputs!$B$5,Q6-Inputs!$B$5<=Inputs!$B$16),FALSE),"IN ZONE: earnings soon, wait",IF(N(M6)<=J6,"IN ZONE: analysts see no upside",IF(J6<=W6,"IN ZONE: at/below buy target - research","IN ZONE: research"))))))) | AD6: =IFERROR(INDEX('Rank Calc'!$P$5:$P$53,MATCH($A6,'Rank Calc'!$A$5:$A$53,0)),"") | AE6: #1 on business quality.
A7: STX | B7: Seagate | C7: Buy Zone | E7: A+ | F7: 4 | G7: 71 COILED | H7: EXPENSIVE -50% (low) | I7: INNOVATING | J7: 700.47 | K7: 803.15 | L7: 690.92 | M7: 1062.55 | N7: 25 | O7: 5 | P7: 0 | Q7: n/a | S7: =J7/L7-1 | T7: =J7/K7-1 | U7: =L7*(1+Inputs!$B$17) | V7: =L7*(1+Inputs!$B$18) | W7: =L7*(1+Inputs!$B$19) | X7: =J7/W7-1 | Y7: =IF(N(M7)>0,M7/W7-1,"") | Z7: =U7 | AA7: =IFERROR(IF(N(M7)>W7,(M7-W7)/(W7-Z7),""),"") | AB7: =IFERROR(N7/(N7+O7+P7),"") | AC7: =IF(D7="HELD","HELD: see Holdings sheet",IF(IF(ISNUMBER(R7),Inputs!$B$5<R7,FALSE),"WASH-SALE LOCK until "&TEXT(R7,"m/d"),IF(J7<U7,"BELOW ZONE: wait for 200-day reclaim",IF(J7>V7,"ABOVE ZONE: extended, wait",IF(IF(ISNUMBER(Q7),AND(Q7>Inputs!$B$5,Q7-Inputs!$B$5<=Inputs!$B$16),FALSE),"IN ZONE: earnings soon, wait",IF(N(M7)<=J7,"IN ZONE: analysts see no upside",IF(J7<=W7,"IN ZONE: at/below buy target - research","IN ZONE: research"))))))) | AD7: =IFERROR(INDEX('Rank Calc'!$P$5:$P$53,MATCH($A7,'Rank Calc'!$A$5:$A$53,0)),"") | AE7: Falling wedge forming; -4.1% after hours.
A8: SCCO | B8: Southern Copper | C8: Buy Zone | E8: A+ | F8: 8 | G8: 71 COILED | H8: EXPENSIVE -38% (high) | I8: STABLE | J8: 191.75 | K8: 201.33 | L8: 189.09 | M8: 176.66 | N8: 1 | O8: 8 | P8: 10 | Q8: n/a | S8: =J8/L8-1 | T8: =J8/K8-1 | U8: =L8*(1+Inputs!$B$17) | V8: =L8*(1+Inputs!$B$18) | W8: =L8*(1+Inputs!$B$19) | X8: =J8/W8-1 | Y8: =IF(N(M8)>0,M8/W8-1,"") | Z8: =U8 | AA8: =IFERROR(IF(N(M8)>W8,(M8-W8)/(W8-Z8),""),"") | AB8: =IFERROR(N8/(N8+O8+P8),"") | AC8: =IF(D8="HELD","HELD: see Holdings sheet",IF(IF(ISNUMBER(R8),Inputs!$B$5<R8,FALSE),"WASH-SALE LOCK until "&TEXT(R8,"m/d"),IF(J8<U8,"BELOW ZONE: wait for 200-day reclaim",IF(J8>V8,"ABOVE ZONE: extended, wait",IF(IF(ISNUMBER(Q8),AND(Q8>Inputs!$B$5,Q8-Inputs!$B$5<=Inputs!$B$16),FALSE),"IN ZONE: earnings soon, wait",IF(N(M8)<=J8,"IN ZONE: analysts see no upside",IF(J8<=W8,"IN ZONE: at/below buy target - research","IN ZONE: research"))))))) | AD8: =IFERROR(INDEX('Rank Calc'!$P$5:$P$53,MATCH($A8,'Rank Calc'!$A$5:$A$53,0)),"") | AE8: Analyst mean target is BELOW price; 10 Sells.
A9: FNV | B9: Franco-Nevada | C9: Buy Zone | E9: A | F9: 11 | G9: 71 COILED | H9: FAIR +1% (med) | I9: STABLE | J9: 231.6 | K9: 252.44 | L9: 240.07 | M9: 287.68 | N9: 7 | O9: 3 | P9: 1 | Q9: 46337 | S9: =J9/L9-1 | T9: =J9/K9-1 | U9: =L9*(1+Inputs!$B$17) | V9: =L9*(1+Inputs!$B$18) | W9: =L9*(1+Inputs!$B$19) | X9: =J9/W9-1 | Y9: =IF(N(M9)>0,M9/W9-1,"") | Z9: =U9 | AA9: =IFERROR(IF(N(M9)>W9,(M9-W9)/(W9-Z9),""),"") | AB9: =IFERROR(N9/(N9+O9+P9),"") | AC9: =IF(D9="HELD","HELD: see Holdings sheet",IF(IF(ISNUMBER(R9),Inputs!$B$5<R9,FALSE),"WASH-SALE LOCK until "&TEXT(R9,"m/d"),IF(J9<U9,"BELOW ZONE: wait for 200-day reclaim",IF(J9>V9,"ABOVE ZONE: extended, wait",IF(IF(ISNUMBER(Q9),AND(Q9>Inputs!$B$5,Q9-Inputs!$B$5<=Inputs!$B$16),FALSE),"IN ZONE: earnings soon, wait",IF(N(M9)<=J9,"IN ZONE: analysts see no upside",IF(J9<=W9,"IN ZONE: at/below buy target - research","IN ZONE: research"))))))) | AD9: =IFERROR(INDEX('Rank Calc'!$P$5:$P$53,MATCH($A9,'Rank Calc'!$A$5:$A$53,0)),"") | AE9: Gold royalty.
A10: AVGO | B10: Broadcom | C10: Buy Zone | E10: A+ | F10: 7 | G10: 57 PULLING BACK | H10: EXPENSIVE -49% (med) | I10: DISRUPTOR | J10: 345 | K10: 353.7 | L10: 367.78 | M10: 532.31 | N10: 53 | O10: 2 | P10: 0 | Q10: 46365 | R10: 46348 | S10: =J10/L10-1 | T10: =J10/K10-1 | U10: =L10*(1+Inputs!$B$17) | V10: =L10*(1+Inputs!$B$18) | W10: =L10*(1+Inputs!$B$19) | X10: =J10/W10-1 | Y10: =IF(N(M10)>0,M10/W10-1,"") | Z10: =U10 | AA10: =IFERROR(IF(N(M10)>W10,(M10-W10)/(W10-Z10),""),"") | AB10: =IFERROR(N10/(N10+O10+P10),"") | AC10: =IF(D10="HELD","HELD: see Holdings sheet",IF(IF(ISNUMBER(R10),Inputs!$B$5<R10,FALSE),"WASH-SALE LOCK until "&TEXT(R10,"m/d"),IF(J10<U10,"BELOW ZONE: wait for 200-day reclaim",IF(J10>V10,"ABOVE ZONE: extended, wait",IF(IF(ISNUMBER(Q10),AND(Q10>Inputs!$B$5,Q10-Inputs!$B$5<=Inputs!$B$16),FALSE),"IN ZONE: earnings soon, wait",IF(N(M10)<=J10,"IN ZONE: analysts see no upside",IF(J10<=W10,"IN ZONE: at/below buy target - research","IN ZONE: research"))))))) | AD10: =IFERROR(INDEX('Rank Calc'!$P$5:$P$53,MATCH($A10,'Rank Calc'!$A$5:$A$53,0)),"") | AE10: Falling wedge forming; thesis intact 9/30. -3.7% after hours.
A11: HOOD | B11: Robinhood Markets | C11: Buy Zone | D11: HELD | E11: A | F11: 14 | G11: 57 PULLING BACK | H11: n/a | I11: DISRUPTOR | J11: 91.59 | K11: 108.69 | L11: 92.76 | M11: 133.63 | N11: 30 | O11: 5 | P11: 2 | Q11: n/a | R11: 46354 | S11: =J11/L11-1 | T11: =J11/K11-1 | U11: =L11*(1+Inputs!$B$17) | V11: =L11*(1+Inputs!$B$18) | W11: =L11*(1+Inputs!$B$19) | X11: =J11/W11-1 | Y11: =IF(N(M11)>0,M11/W11-1,"") | Z11: =U11 | AA11: =IFERROR(IF(N(M11)>W11,(M11-W11)/(W11-Z11),""),"") | AB11: =IFERROR(N11/(N11+O11+P11),"") | AC11: =IF(D11="HELD","HELD: see Holdings sheet",IF(IF(ISNUMBER(R11),Inputs!$B$5<R11,FALSE),"WASH-SALE LOCK until "&TEXT(R11,"m/d"),IF(J11<U11,"BELOW ZONE: wait for 200-day reclaim",IF(J11>V11,"ABOVE ZONE: extended, wait",IF(IF(ISNUMBER(Q11),AND(Q11>Inputs!$B$5,Q11-Inputs!$B$5<=Inputs!$B$16),FALSE),"IN ZONE: earnings soon, wait",IF(N(M11)<=J11,"IN ZONE: analysts see no upside",IF(J11<=W11,"IN ZONE: at/below buy target - research","IN ZONE: research"))))))) | AD11: =IFERROR(INDEX('Rank Calc'!$P$5:$P$53,MATCH($A11,'Rank Calc'!$A$5:$A$53,0)),"") | AE11: Fractional leftover (<$1).
A12: NEM | B12: Newmont | C12: Buy Zone | E12: A | F12: 15 | G12: 57 PULLING BACK | H12: RICH -25% (low) | I12: STABLE | J12: 111.8 | K12: 121.1 | L12: 112.49 | M12: 137.61 | N12: 24 | O12: 4 | P12: 2 | Q12: n/a | S12: =J12/L12-1 | T12: =J12/K12-1 | U12: =L12*(1+Inputs!$B$17) | V12: =L12*(1+Inputs!$B$18) | W12: =L12*(1+Inputs!$B$19) | X12: =J12/W12-1 | Y12: =IF(N(M12)>0,M12/W12-1,"") | Z12: =U12 | AA12: =IFERROR(IF(N(M12)>W12,(M12-W12)/(W12-Z12),""),"") | AB12: =IFERROR(N12/(N12+O12+P12),"") | AC12: =IF(D12="HELD","HELD: see Holdings sheet",IF(IF(ISNUMBER(R12),Inputs!$B$5<R12,FALSE),"WASH-SALE LOCK until "&TEXT(R12,"m/d"),IF(J12<U12,"BELOW ZONE: wait for 200-day reclaim",IF(J12>V12,"ABOVE ZONE: extended, wait",IF(IF(ISNUMBER(Q12),AND(Q12>Inputs!$B$5,Q12-Inputs!$B$5<=Inputs!$B$16),FALSE),"IN ZONE: earnings soon, wait",IF(N(M12)<=J12,"IN ZONE: analysts see no upside",IF(J12<=W12,"IN ZONE: at/below buy target - research","IN ZONE: research"))))))) | AD12: =IFERROR(INDEX('Rank Calc'!$P$5:$P$53,MATCH($A12,'Rank Calc'!$A$5:$A$53,0)),"")
A13: ASML | B13: ASML Holding | C13: Buy Zone | E13: A+ | F13: 9 | G13: 43 PULLING BACK | H13: EXPENSIVE -34% (med) | I13: INNOVATING | J13: 1675.7 | K13: 1708.14 | L13: 1595.65 | M13: 2408.5 | N13: 37 | O13: 4 | P13: 2 | Q13: 46414 | S13: =J13/L13-1 | T13: =J13/K13-1 | U13: =L13*(1+Inputs!$B$17) | V13: =L13*(1+Inputs!$B$18) | W13: =L13*(1+Inputs!$B$19) | X13: =J13/W13-1 | Y13: =IF(N(M13)>0,M13/W13-1,"") | Z13: =U13 | AA13: =IFERROR(IF(N(M13)>W13,(M13-W13)/(W13-Z13),""),"") | AB13: =IFERROR(N13/(N13+O13+P13),"") | AC13: =IF(D13="HELD","HELD: see Holdings sheet",IF(IF(ISNUMBER(R13),Inputs!$B$5<R13,FALSE),"WASH-SALE LOCK until "&TEXT(R13,"m/d"),IF(J13<U13,"BELOW ZONE: wait for 200-day reclaim",IF(J13>V13,"ABOVE ZONE: extended, wait",IF(IF(ISNUMBER(Q13),AND(Q13>Inputs!$B$5,Q13-Inputs!$B$5<=Inputs!$B$16),FALSE),"IN ZONE: earnings soon, wait",IF(N(M13)<=J13,"IN ZONE: analysts see no upside",IF(J13<=W13,"IN ZONE: at/below buy target - research","IN ZONE: research"))))))) | AD13: =IFERROR(INDEX('Rank Calc'!$P$5:$P$53,MATCH($A13,'Rank Calc'!$A$5:$A$53,0)),"") | AE13: Double bottom forming; -3.6% after hours.
A14: AMAT | B14: Applied Materials | C14: Buy Zone | E14: A | F14: 17 | G14: 43 PULLING BACK | H14: EXPENSIVE -50% (med) | I14: INNOVATING | J14: 421.66 | K14: 459.67 | L14: 444.04 | M14: 651.64 | N14: 35 | O14: 5 | P14: 0 | Q14: 46338 | S14: =J14/L14-1 | T14: =J14/K14-1 | U14: =L14*(1+Inputs!$B$17) | V14: =L14*(1+Inputs!$B$18) | W14: =L14*(1+Inputs!$B$19) | X14: =J14/W14-1 | Y14: =IF(N(M14)>0,M14/W14-1,"") | Z14: =U14 | AA14: =IFERROR(IF(N(M14)>W14,(M14-W14)/(W14-Z14),""),"") | AB14: =IFERROR(N14/(N14+O14+P14),"") | AC14: =IF(D14="HELD","HELD: see Holdings sheet",IF(IF(ISNUMBER(R14),Inputs!$B$5<R14,FALSE),"WASH-SALE LOCK until "&TEXT(R14,"m/d"),IF(J14<U14,"BELOW ZONE: wait for 200-day reclaim",IF(J14>V14,"ABOVE ZONE: extended, wait",IF(IF(ISNUMBER(Q14),AND(Q14>Inputs!$B$5,Q14-Inputs!$B$5<=Inputs!$B$16),FALSE),"IN ZONE: earnings soon, wait",IF(N(M14)<=J14,"IN ZONE: analysts see no upside",IF(J14<=W14,"IN ZONE: at/below buy target - research","IN ZONE: research"))))))) | AD14: =IFERROR(INDEX('Rank Calc'!$P$5:$P$53,MATCH($A14,'Rank Calc'!$A$5:$A$53,0)),"") | AE14: -4.5% after hours.
A15: KEYS | B15: Keysight | C15: Buy Zone | E15: A | F15: 23 | G15: 43 PULLING BACK | H15: EXPENSIVE -36% (med) | I15: AT RISK | J15: 329.84 | K15: 341.12 | L15: 316.26 | M15: 424.18 | N15: 13 | O15: 2 | P15: 0 | Q15: 46345 | S15: =J15/L15-1 | T15: =J15/K15-1 | U15: =L15*(1+Inputs!$B$17) | V15: =L15*(1+Inputs!$B$18) | W15: =L15*(1+Inputs!$B$19) | X15: =J15/W15-1 | Y15: =IF(N(M15)>0,M15/W15-1,"") | Z15: =U15 | AA15: =IFERROR(IF(N(M15)>W15,(M15-W15)/(W15-Z15),""),"") | AB15: =IFERROR(N15/(N15+O15+P15),"") | AC15: =IF(D15="HELD","HELD: see Holdings sheet",IF(IF(ISNUMBER(R15),Inputs!$B$5<R15,FALSE),"WASH-SALE LOCK until "&TEXT(R15,"m/d"),IF(J15<U15,"BELOW ZONE: wait for 200-day reclaim",IF(J15>V15,"ABOVE ZONE: extended, wait",IF(IF(ISNUMBER(Q15),AND(Q15>Inputs!$B$5,Q15-Inputs!$B$5<=Inputs!$B$16),FALSE),"IN ZONE: earnings soon, wait",IF(N(M15)<=J15,"IN ZONE: analysts see no upside",IF(J15<=W15,"IN ZONE: at/below buy target - research","IN ZONE: research"))))))) | AD15: =IFERROR(INDEX('Rank Calc'!$P$5:$P$53,MATCH($A15,'Rank Calc'!$A$5:$A$53,0)),"")
A16: META | B16: Meta Platforms | C16: Buy Zone | D16: HELD | E16: A+ | F16: 5 | G16: 29 MIXED | H16: FAIR -2% (med) | I16: INNOVATING | J16: 624.52 | K16: 668.6 | L16: 632.11 | M16: 850.51 | N16: 65 | O16: 6 | P16: 1 | Q16: n/a | R16: 46354 | S16: =J16/L16-1 | T16: =J16/K16-1 | U16: =L16*(1+Inputs!$B$17) | V16: =L16*(1+Inputs!$B$18) | W16: =L16*(1+Inputs!$B$19) | X16: =J16/W16-1 | Y16: =IF(N(M16)>0,M16/W16-1,"") | Z16: =U16 | AA16: =IFERROR(IF(N(M16)>W16,(M16-W16)/(W16-Z16),""),"") | AB16: =IFERROR(N16/(N16+O16+P16),"") | AC16: =IF(D16="HELD","HELD: see Holdings sheet",IF(IF(ISNUMBER(R16),Inputs!$B$5<R16,FALSE),"WASH-SALE LOCK until "&TEXT(R16,"m/d"),IF(J16<U16,"BELOW ZONE: wait for 200-day reclaim",IF(J16>V16,"ABOVE ZONE: extended, wait",IF(IF(ISNUMBER(Q16),AND(Q16>Inputs!$B$5,Q16-Inputs!$B$5<=Inputs!$B$16),FALSE),"IN ZONE: earnings soon, wait",IF(N(M16)<=J16,"IN ZONE: analysts see no upside",IF(J16<=W16,"IN ZONE: at/below buy target - research","IN ZONE: research"))))))) | AD16: =IFERROR(INDEX('Rank Calc'!$P$5:$P$53,MATCH($A16,'Rank Calc'!$A$5:$A$53,0)),"") | AE16: Already held (~15% of the joint account).
A17: WES | B17: Western Midstream | C17: Buy Zone | E17: A+ | F17: 6 | G17: 29 MIXED | H17: RICH -20% (high) | I17: STABLE | J17: 45.82 | K17: 46.5 | L17: 44.12 | M17: 49.54 | N17: 5 | O17: 10 | P17: 2 | Q17: 46330 | S17: =J17/L17-1 | T17: =J17/K17-1 | U17: =L17*(1+Inputs!$B$17) | V17: =L17*(1+Inputs!$B$18) | W17: =L17*(1+Inputs!$B$19) | X17: =J17/W17-1 | Y17: =IF(N(M17)>0,M17/W17-1,"") | Z17: =U17 | AA17: =IFERROR(IF(N(M17)>W17,(M17-W17)/(W17-Z17),""),"") | AB17: =IFERROR(N17/(N17+O17+P17),"") | AC17: =IF(D17="HELD","HELD: see Holdings sheet",IF(IF(ISNUMBER(R17),Inputs!$B$5<R17,FALSE),"WASH-SALE LOCK until "&TEXT(R17,"m/d"),IF(J17<U17,"BELOW ZONE: wait for 200-day reclaim",IF(J17>V17,"ABOVE ZONE: extended, wait",IF(IF(ISNUMBER(Q17),AND(Q17>Inputs!$B$5,Q17-Inputs!$B$5<=Inputs!$B$16),FALSE),"IN ZONE: earnings soon, wait",IF(N(M17)<=J17,"IN ZONE: analysts see no upside",IF(J17<=W17,"IN ZONE: at/below buy target - research","IN ZONE: research"))))))) | AD17: =IFERROR(INDEX('Rank Calc'!$P$5:$P$53,MATCH($A17,'Rank Calc'!$A$5:$A$53,0)),"") | AE17: Double bottom near trigger 46.42. Analysts mostly Hold.
A18: RGLD | B18: Royal Gold | C18: Buy Zone | E18: A | F18: 12 | G18: 29 MIXED | H18: FAIR +7% (high) | I18: STABLE | J18: 236.83 | K18: 246.65 | L18: 241.42 | M18: 310.08 | N18: 11 | O18: 3 | P18: 1 | Q18: n/a | S18: =J18/L18-1 | T18: =J18/K18-1 | U18: =L18*(1+Inputs!$B$17) | V18: =L18*(1+Inputs!$B$18) | W18: =L18*(1+Inputs!$B$19) | X18: =J18/W18-1 | Y18: =IF(N(M18)>0,M18/W18-1,"") | Z18: =U18 | AA18: =IFERROR(IF(N(M18)>W18,(M18-W18)/(W18-Z18),""),"") | AB18: =IFERROR(N18/(N18+O18+P18),"") | AC18: =IF(D18="HELD","HELD: see Holdings sheet",IF(IF(ISNUMBER(R18),Inputs!$B$5<R18,FALSE),"WASH-SALE LOCK until "&TEXT(R18,"m/d"),IF(J18<U18,"BELOW ZONE: wait for 200-day reclaim",IF(J18>V18,"ABOVE ZONE: extended, wait",IF(IF(ISNUMBER(Q18),AND(Q18>Inputs!$B$5,Q18-Inputs!$B$5<=Inputs!$B$16),FALSE),"IN ZONE: earnings soon, wait",IF(N(M18)<=J18,"IN ZONE: analysts see no upside",IF(J18<=W18,"IN ZONE: at/below buy target - research","IN ZONE: research"))))))) | AD18: =IFERROR(INDEX('Rank Calc'!$P$5:$P$53,MATCH($A18,'Rank Calc'!$A$5:$A$53,0)),"")
A19: WDC | B19: Western Digital | C19: Buy Zone | E19: A | F19: 13 | G19: 29 MIXED | H19: EXPENSIVE -50% (low) | I19: DISRUPTOR | J19: 395.41 | K19: 423.52 | L19: 418.23 | M19: 621.78 | N19: 22 | O19: 8 | P19: 0 | Q19: n/a | S19: =J19/L19-1 | T19: =J19/K19-1 | U19: =L19*(1+Inputs!$B$17) | V19: =L19*(1+Inputs!$B$18) | W19: =L19*(1+Inputs!$B$19) | X19: =J19/W19-1 | Y19: =IF(N(M19)>0,M19/W19-1,"") | Z19: =U19 | AA19: =IFERROR(IF(N(M19)>W19,(M19-W19)/(W19-Z19),""),"") | AB19: =IFERROR(N19/(N19+O19+P19),"") | AC19: =IF(D19="HELD","HELD: see Holdings sheet",IF(IF(ISNUMBER(R19),Inputs!$B$5<R19,FALSE),"WASH-SALE LOCK until "&TEXT(R19,"m/d"),IF(J19<U19,"BELOW ZONE: wait for 200-day reclaim",IF(J19>V19,"ABOVE ZONE: extended, wait",IF(IF(ISNUMBER(Q19),AND(Q19>Inputs!$B$5,Q19-Inputs!$B$5<=Inputs!$B$16),FALSE),"IN ZONE: earnings soon, wait",IF(N(M19)<=J19,"IN ZONE: analysts see no upside",IF(J19<=W19,"IN ZONE: at/below buy target - research","IN ZONE: research"))))))) | AD19: =IFERROR(INDEX('Rank Calc'!$P$5:$P$53,MATCH($A19,'Rank Calc'!$A$5:$A$53,0)),"") | AE19: -4.5% after hours.
A20: NBIX | B20: Neurocrine Biosciences | C20: Buy Zone | E20: A | F20: 18 | G20: 29 MIXED | H20: DEEP VALUE +100% (low) | I20: DISRUPTOR | J20: 146.38 | K20: 146.75 | L20: 147.32 | M20: 207.37 | N20: 27 | O20: 4 | P20: 0 | Q20: 46328 | S20: =J20/L20-1 | T20: =J20/K20-1 | U20: =L20*(1+Inputs!$B$17) | V20: =L20*(1+Inputs!$B$18) | W20: =L20*(1+Inputs!$B$19) | X20: =J20/W20-1 | Y20: =IF(N(M20)>0,M20/W20-1,"") | Z20: =U20 | AA20: =IFERROR(IF(N(M20)>W20,(M20-W20)/(W20-Z20),""),"") | AB20: =IFERROR(N20/(N20+O20+P20),"") | AC20: =IF(D20="HELD","HELD: see Holdings sheet",IF(IF(ISNUMBER(R20),Inputs!$B$5<R20,FALSE),"WASH-SALE LOCK until "&TEXT(R20,"m/d"),IF(J20<U20,"BELOW ZONE: wait for 200-day reclaim",IF(J20>V20,"ABOVE ZONE: extended, wait",IF(IF(ISNUMBER(Q20),AND(Q20>Inputs!$B$5,Q20-Inputs!$B$5<=Inputs!$B$16),FALSE),"IN ZONE: earnings soon, wait",IF(N(M20)<=J20,"IN ZONE: analysts see no upside",IF(J20<=W20,"IN ZONE: at/below buy target - research","IN ZONE: research"))))))) | AD20: =IFERROR(INDEX('Rank Calc'!$P$5:$P$53,MATCH($A20,'Rank Calc'!$A$5:$A$53,0)),"") | AE20: Reports 11/2.
A21: CDNS | B21: Cadence Design | C21: Buy Zone | D21: HELD | E21: A | F21: 19 | G21: 29 MIXED | H21: FAIR -9% (high) | I21: INNOVATING | J21: 342.75 | K21: 320.24 | L21: 327.46 | M21: 415.04 | N21: 25 | O21: 3 | P21: 0 | Q21: n/a | S21: =J21/L21-1 | T21: =J21/K21-1 | U21: =L21*(1+Inputs!$B$17) | V21: =L21*(1+Inputs!$B$18) | W21: =L21*(1+Inputs!$B$19) | X21: =J21/W21-1 | Y21: =IF(N(M21)>0,M21/W21-1,"") | Z21: =U21 | AA21: =IFERROR(IF(N(M21)>W21,(M21-W21)/(W21-Z21),""),"") | AB21: =IFERROR(N21/(N21+O21+P21),"") | AC21: =IF(D21="HELD","HELD: see Holdings sheet",IF(IF(ISNUMBER(R21),Inputs!$B$5<R21,FALSE),"WASH-SALE LOCK until "&TEXT(R21,"m/d"),IF(J21<U21,"BELOW ZONE: wait for 200-day reclaim",IF(J21>V21,"ABOVE ZONE: extended, wait",IF(IF(ISNUMBER(Q21),AND(Q21>Inputs!$B$5,Q21-Inputs!$B$5<=Inputs!$B$16),FALSE),"IN ZONE: earnings soon, wait",IF(N(M21)<=J21,"IN ZONE: analysts see no upside",IF(J21<=W21,"IN ZONE: at/below buy target - research","IN ZONE: research"))))))) | AD21: =IFERROR(INDEX('Rank Calc'!$P$5:$P$53,MATCH($A21,'Rank Calc'!$A$5:$A$53,0)),"") | AE21: Target agreement LOW: fundamental and Robinhood targets 35% apart.
A22: ADBE | B22: Adobe | C22: Buy Zone | E22: A | F22: 22 | G22: 29 MIXED | H22: DEEP VALUE +100% (low) | I22: AT RISK | J22: 248.12 | K22: 254.84 | L22: 250.71 | M22: 269.5 | N22: 11 | O22: 25 | P22: 5 | Q22: n/a | S22: =J22/L22-1 | T22: =J22/K22-1 | U22: =L22*(1+Inputs!$B$17) | V22: =L22*(1+Inputs!$B$18) | W22: =L22*(1+Inputs!$B$19) | X22: =J22/W22-1 | Y22: =IF(N(M22)>0,M22/W22-1,"") | Z22: =U22 | AA22: =IFERROR(IF(N(M22)>W22,(M22-W22)/(W22-Z22),""),"") | AB22: =IFERROR(N22/(N22+O22+P22),"") | AC22: =IF(D22="HELD","HELD: see Holdings sheet",IF(IF(ISNUMBER(R22),Inputs!$B$5<R22,FALSE),"WASH-SALE LOCK until "&TEXT(R22,"m/d"),IF(J22<U22,"BELOW ZONE: wait for 200-day reclaim",IF(J22>V22,"ABOVE ZONE: extended, wait",IF(IF(ISNUMBER(Q22),AND(Q22>Inputs!$B$5,Q22-Inputs!$B$5<=Inputs!$B$16),FALSE),"IN ZONE: earnings soon, wait",IF(N(M22)<=J22,"IN ZONE: analysts see no upside",IF(J22<=W22,"IN ZONE: at/below buy target - research","IN ZONE: research"))))))) | AD22: =IFERROR(INDEX('Rank Calc'!$P$5:$P$53,MATCH($A22,'Rank Calc'!$A$5:$A$53,0)),"") | AE22: VALUE TRAP? flag: AI design tools pressure; thesis weakened 10/23.
A23: PAC | B23: Grupo Aeroportuario del Pacifico | C23: Buy Zone | E23: A | F23: 10 | G23: 0 EXTENDED | H23: DEEP VALUE +55% (med) | I23: DISRUPTOR | J23: 227.47 | K23: 208.31 | L23: 236.65 | M23: 232.5 | N23: 6 | O23: 7 | P23: 0 | Q23: n/a | S23: =J23/L23-1 | T23: =J23/K23-1 | U23: =L23*(1+Inputs!$B$17) | V23: =L23*(1+Inputs!$B$18) | W23: =L23*(1+Inputs!$B$19) | X23: =J23/W23-1 | Y23: =IF(N(M23)>0,M23/W23-1,"") | Z23: =U23 | AA23: =IFERROR(IF(N(M23)>W23,(M23-W23)/(W23-Z23),""),"") | AB23: =IFERROR(N23/(N23+O23+P23),"") | AC23: =IF(D23="HELD","HELD: see Holdings sheet",IF(IF(ISNUMBER(R23),Inputs!$B$5<R23,FALSE),"WASH-SALE LOCK until "&TEXT(R23,"m/d"),IF(J23<U23,"BELOW ZONE: wait for 200-day reclaim",IF(J23>V23,"ABOVE ZONE: extended, wait",IF(IF(ISNUMBER(Q23),AND(Q23>Inputs!$B$5,Q23-Inputs!$B$5<=Inputs!$B$16),FALSE),"IN ZONE: earnings soon, wait",IF(N(M23)<=J23,"IN ZONE: analysts see no upside",IF(J23<=W23,"IN ZONE: at/below buy target - research","IN ZONE: research"))))))) | AD23: =IFERROR(INDEX('Rank Calc'!$P$5:$P$53,MATCH($A23,'Rank Calc'!$A$5:$A$53,0)),"") | AE23: Analyst target last updated 2020: stale.
A24: PSA | B24: Public Storage | C24: Buy Zone | E24: A | F24: 16 | G24: 0 EXTENDED | H24: RICH -13% (high) | I24: STABLE | J24: 317.06 | K24: 298.61 | L24: 302.64 | M24: 330.06 | N24: 7 | O24: 16 | P24: 0 | Q24: n/a | S24: =J24/L24-1 | T24: =J24/K24-1 | U24: =L24*(1+Inputs!$B$17) | V24: =L24*(1+Inputs!$B$18) | W24: =L24*(1+Inputs!$B$19) | X24: =J24/W24-1 | Y24: =IF(N(M24)>0,M24/W24-1,"") | Z24: =U24 | AA24: =IFERROR(IF(N(M24)>W24,(M24-W24)/(W24-Z24),""),"") | AB24: =IFERROR(N24/(N24+O24+P24),"") | AC24: =IF(D24="HELD","HELD: see Holdings sheet",IF(IF(ISNUMBER(R24),Inputs!$B$5<R24,FALSE),"WASH-SALE LOCK until "&TEXT(R24,"m/d"),IF(J24<U24,"BELOW ZONE: wait for 200-day reclaim",IF(J24>V24,"ABOVE ZONE: extended, wait",IF(IF(ISNUMBER(Q24),AND(Q24>Inputs!$B$5,Q24-Inputs!$B$5<=Inputs!$B$16),FALSE),"IN ZONE: earnings soon, wait",IF(N(M24)<=J24,"IN ZONE: analysts see no upside",IF(J24<=W24,"IN ZONE: at/below buy target - research","IN ZONE: research"))))))) | AD24: =IFERROR(INDEX('Rank Calc'!$P$5:$P$53,MATCH($A24,'Rank Calc'!$A$5:$A$53,0)),"")
A25: ISRG | B25: Intuitive Surgical | C25: Buy Zone | E25: A | F25: 20 | G25: 0 EXTENDED | H25: DEEP VALUE +44% (high) | I25: AT RISK | J25: 448.76 | K25: 400.3 | L25: 433.61 | M25: 489.57 | N25: 21 | O25: 8 | P25: 2 | Q25: n/a | S25: =J25/L25-1 | T25: =J25/K25-1 | U25: =L25*(1+Inputs!$B$17) | V25: =L25*(1+Inputs!$B$18) | W25: =L25*(1+Inputs!$B$19) | X25: =J25/W25-1 | Y25: =IF(N(M25)>0,M25/W25-1,"") | Z25: =U25 | AA25: =IFERROR(IF(N(M25)>W25,(M25-W25)/(W25-Z25),""),"") | AB25: =IFERROR(N25/(N25+O25+P25),"") | AC25: =IF(D25="HELD","HELD: see Holdings sheet",IF(IF(ISNUMBER(R25),Inputs!$B$5<R25,FALSE),"WASH-SALE LOCK until "&TEXT(R25,"m/d"),IF(J25<U25,"BELOW ZONE: wait for 200-day reclaim",IF(J25>V25,"ABOVE ZONE: extended, wait",IF(IF(ISNUMBER(Q25),AND(Q25>Inputs!$B$5,Q25-Inputs!$B$5<=Inputs!$B$16),FALSE),"IN ZONE: earnings soon, wait",IF(N(M25)<=J25,"IN ZONE: analysts see no upside",IF(J25<=W25,"IN ZONE: at/below buy target - research","IN ZONE: research"))))))) | AD25: =IFERROR(INDEX('Rank Calc'!$P$5:$P$53,MATCH($A25,'Rank Calc'!$A$5:$A$53,0)),"") | AE25: VALUE TRAP? flag from the quant grade; research says innovating.
A26: TROW | B26: T. Rowe Price | C26: Buy Zone | E26: A | F26: 21 | G26: 0 EXTENDED | H26: DEEP VALUE +34% (med) | I26: STABLE | J26: 106.63 | K26: 105.77 | L26: 103.68 | M26: 102.83 | N26: 0 | O26: 10 | P26: 5 | Q26: n/a | S26: =J26/L26-1 | T26: =J26/K26-1 | U26: =L26*(1+Inputs!$B$17) | V26: =L26*(1+Inputs!$B$18) | W26: =L26*(1+Inputs!$B$19) | X26: =J26/W26-1 | Y26: =IF(N(M26)>0,M26/W26-1,"") | Z26: =U26 | AA26: =IFERROR(IF(N(M26)>W26,(M26-W26)/(W26-Z26),""),"") | AB26: =IFERROR(N26/(N26+O26+P26),"") | AC26: =IF(D26="HELD","HELD: see Holdings sheet",IF(IF(ISNUMBER(R26),Inputs!$B$5<R26,FALSE),"WASH-SALE LOCK until "&TEXT(R26,"m/d"),IF(J26<U26,"BELOW ZONE: wait for 200-day reclaim",IF(J26>V26,"ABOVE ZONE: extended, wait",IF(IF(ISNUMBER(Q26),AND(Q26>Inputs!$B$5,Q26-Inputs!$B$5<=Inputs!$B$16),FALSE),"IN ZONE: earnings soon, wait",IF(N(M26)<=J26,"IN ZONE: analysts see no upside",IF(J26<=W26,"IN ZONE: at/below buy target - research","IN ZONE: research"))))))) | AD26: =IFERROR(INDEX('Rank Calc'!$P$5:$P$53,MATCH($A26,'Rank Calc'!$A$5:$A$53,0)),"") | AE26: VALUE TRAP? Losing assets to passive funds. No Buy ratings.
A27: SKHY | B27: SK hynix (ADR) | C27: Buy Zone | E27: A+ | F27: 2 | G27: n/a | H27: DEEP VALUE +100% (low) | I27: DISRUPTOR | J27: 162.09 | K27: 169.17 | L27: 154.83 | M27: 263.91 | N27: 12 | O27: 2 | P27: 0 | Q27: n/a | R27: 46348 | S27: =J27/L27-1 | T27: =J27/K27-1 | U27: =L27*(1+Inputs!$B$17) | V27: =L27*(1+Inputs!$B$18) | W27: =L27*(1+Inputs!$B$19) | X27: =J27/W27-1 | Y27: =IF(N(M27)>0,M27/W27-1,"") | Z27: =U27 | AA27: =IFERROR(IF(N(M27)>W27,(M27-W27)/(W27-Z27),""),"") | AB27: =IFERROR(N27/(N27+O27+P27),"") | AC27: =IF(D27="HELD","HELD: see Holdings sheet",IF(IF(ISNUMBER(R27),Inputs!$B$5<R27,FALSE),"WASH-SALE LOCK until "&TEXT(R27,"m/d"),IF(J27<U27,"BELOW ZONE: wait for 200-day reclaim",IF(J27>V27,"ABOVE ZONE: extended, wait",IF(IF(ISNUMBER(Q27),AND(Q27>Inputs!$B$5,Q27-Inputs!$B$5<=Inputs!$B$16),FALSE),"IN ZONE: earnings soon, wait",IF(N(M27)<=J27,"IN ZONE: analysts see no upside",IF(J27<=W27,"IN ZONE: at/below buy target - research","IN ZONE: research"))))))) | AD27: =IFERROR(INDEX('Rank Calc'!$P$5:$P$53,MATCH($A27,'Rank Calc'!$A$5:$A$53,0)),"") | AE27: -5.3% after hours.
A28: MOD | B28: Modine Manufacturing | C28: Re-buy | E28: n/a | G28: WAIT (re-buy stage) | H28: EXPENSIVE -50% (low) | I28: INNOVATING | J28: 138.79 | K28: 175.88 | L28: 216.14 | M28: 282.48 | N28: 12 | O28: 0 | P28: 0 | Q28: n/a | R28: 46340 | S28: =J28/L28-1 | T28: =J28/K28-1 | U28: =L28*(1+Inputs!$B$17) | V28: =L28*(1+Inputs!$B$18) | W28: =L28*(1+Inputs!$B$19) | X28: =J28/W28-1 | Y28: =IF(N(M28)>0,M28/W28-1,"") | Z28: =U28 | AA28: =IFERROR(IF(N(M28)>W28,(M28-W28)/(W28-Z28),""),"") | AB28: =IFERROR(N28/(N28+O28+P28),"") | AC28: =IF(D28="HELD","HELD: see Holdings sheet",IF(IF(ISNUMBER(R28),Inputs!$B$5<R28,FALSE),"WASH-SALE LOCK until "&TEXT(R28,"m/d"),IF(J28<U28,"BELOW ZONE: wait for 200-day reclaim",IF(J28>V28,"ABOVE ZONE: extended, wait",IF(IF(ISNUMBER(Q28),AND(Q28>Inputs!$B$5,Q28-Inputs!$B$5<=Inputs!$B$16),FALSE),"IN ZONE: earnings soon, wait",IF(N(M28)<=J28,"IN ZONE: analysts see no upside",IF(J28<=W28,"IN ZONE: at/below buy target - research","IN ZONE: research"))))))) | AD28: =IFERROR(INDEX('Rank Calc'!$P$5:$P$53,MATCH($A28,'Rank Calc'!$A$5:$A$53,0)),"") | AE28: Sold 10/14 @ 162.10 at a loss: do not rebuy before the wash-sale date.
A29: SPG | B29: Simon Property Group | C29: New industry | E29: A | G29: Malls REIT | H29: FAIR -2% (high) | I29: STABLE | J29: 215.72 | K29: 207.18 | L29: 205.72 | M29: 228.89 | N29: 7 | O29: 15 | P29: 0 | Q29: 46331 | S29: =J29/L29-1 | T29: =J29/K29-1 | U29: =L29*(1+Inputs!$B$17) | V29: =L29*(1+Inputs!$B$18) | W29: =L29*(1+Inputs!$B$19) | X29: =J29/W29-1 | Y29: =IF(N(M29)>0,M29/W29-1,"") | Z29: =U29 | AA29: =IFERROR(IF(N(M29)>W29,(M29-W29)/(W29-Z29),""),"") | AB29: =IFERROR(N29/(N29+O29+P29),"") | AC29: =IF(D29="HELD","HELD: see Holdings sheet",IF(IF(ISNUMBER(R29),Inputs!$B$5<R29,FALSE),"WASH-SALE LOCK until "&TEXT(R29,"m/d"),IF(J29<U29,"BELOW ZONE: wait for 200-day reclaim",IF(J29>V29,"ABOVE ZONE: extended, wait",IF(IF(ISNUMBER(Q29),AND(Q29>Inputs!$B$5,Q29-Inputs!$B$5<=Inputs!$B$16),FALSE),"IN ZONE: earnings soon, wait",IF(N(M29)<=J29,"IN ZONE: analysts see no upside",IF(J29<=W29,"IN ZONE: at/below buy target - research","IN ZONE: research"))))))) | AD29: =IFERROR(INDEX('Rank Calc'!$P$5:$P$53,MATCH($A29,'Rank Calc'!$A$5:$A$53,0)),"") | AE29: Malls REIT. Only new name already inside the buy zone. Analysts mostly Hold.
A30: MNST | B30: Monster Beverage | C30: New industry | E30: A | G30: Consumer staples | H30: RICH -10% (med) | I30: STABLE | J30: 46.35 | K30: 44.75 | L30: 43.04 | M30: 50.69 | N30: 14 | O30: 13 | P30: 1 | Q30: 46331 | S30: =J30/L30-1 | T30: =J30/K30-1 | U30: =L30*(1+Inputs!$B$17) | V30: =L30*(1+Inputs!$B$18) | W30: =L30*(1+Inputs!$B$19) | X30: =J30/W30-1 | Y30: =IF(N(M30)>0,M30/W30-1,"") | Z30: =U30 | AA30: =IFERROR(IF(N(M30)>W30,(M30-W30)/(W30-Z30),""),"") | AB30: =IFERROR(N30/(N30+O30+P30),"") | AC30: =IF(D30="HELD","HELD: see Holdings sheet",IF(IF(ISNUMBER(R30),Inputs!$B$5<R30,FALSE),"WASH-SALE LOCK until "&TEXT(R30,"m/d"),IF(J30<U30,"BELOW ZONE: wait for 200-day reclaim",IF(J30>V30,"ABOVE ZONE: extended, wait",IF(IF(ISNUMBER(Q30),AND(Q30>Inputs!$B$5,Q30-Inputs!$B$5<=Inputs!$B$16),FALSE),"IN ZONE: earnings soon, wait",IF(N(M30)<=J30,"IN ZONE: analysts see no upside",IF(J30<=W30,"IN ZONE: at/below buy target - research","IN ZONE: research"))))))) | AD30: =IFERROR(INDEX('Rank Calc'!$P$5:$P$53,MATCH($A30,'Rank Calc'!$A$5:$A$53,0)),"") | AE30: Consumer staples. Rev +20%, net margin 23%. 2-for-1 split Aug 2026.
A31: INCY | B31: Incyte | C31: New industry | E31: A+ | G31: Biotech | H31: DEEP VALUE +100% (low) | I31: INNOVATING | J31: 116.8 | K31: 120.62 | L31: 107.99 | M31: 132.78 | N31: 14 | O31: 15 | P31: 2 | Q31: n/a | S31: =J31/L31-1 | T31: =J31/K31-1 | U31: =L31*(1+Inputs!$B$17) | V31: =L31*(1+Inputs!$B$18) | W31: =L31*(1+Inputs!$B$19) | X31: =J31/W31-1 | Y31: =IF(N(M31)>0,M31/W31-1,"") | Z31: =U31 | AA31: =IFERROR(IF(N(M31)>W31,(M31-W31)/(W31-Z31),""),"") | AB31: =IFERROR(N31/(N31+O31+P31),"") | AC31: =IF(D31="HELD","HELD: see Holdings sheet",IF(IF(ISNUMBER(R31),Inputs!$B$5<R31,FALSE),"WASH-SALE LOCK until "&TEXT(R31,"m/d"),IF(J31<U31,"BELOW ZONE: wait for 200-day reclaim",IF(J31>V31,"ABOVE ZONE: extended, wait",IF(IF(ISNUMBER(Q31),AND(Q31>Inputs!$B$5,Q31-Inputs!$B$5<=Inputs!$B$16),FALSE),"IN ZONE: earnings soon, wait",IF(N(M31)<=J31,"IN ZONE: analysts see no upside",IF(J31<=W31,"IN ZONE: at/below buy target - research","IN ZONE: research"))))))) | AD31: =IFERROR(INDEX('Rank Calc'!$P$5:$P$53,MATCH($A31,'Rank Calc'!$A$5:$A$53,0)),"") | AE31: Biotech. Q3 GAAP loss -$3.86/sh from a one-time $1.23B Vega IPR&D charge; revenue +14%. Analysts split Buy/Hold.
A32: ANET | B32: Arista Networks | C32: New industry | E32: A+ | G32: AI networking | H32: EXPENSIVE -32% (low) | I32: INNOVATING | J32: 184.22 | K32: 195.57 | L32: 164.96 | M32: 248.54 | N32: 35 | O32: 0 | P32: 0 | Q32: 46329 | S32: =J32/L32-1 | T32: =J32/K32-1 | U32: =L32*(1+Inputs!$B$17) | V32: =L32*(1+Inputs!$B$18) | W32: =L32*(1+Inputs!$B$19) | X32: =J32/W32-1 | Y32: =IF(N(M32)>0,M32/W32-1,"") | Z32: =U32 | AA32: =IFERROR(IF(N(M32)>W32,(M32-W32)/(W32-Z32),""),"") | AB32: =IFERROR(N32/(N32+O32+P32),"") | AC32: =IF(D32="HELD","HELD: see Holdings sheet",IF(IF(ISNUMBER(R32),Inputs!$B$5<R32,FALSE),"WASH-SALE LOCK until "&TEXT(R32,"m/d"),IF(J32<U32,"BELOW ZONE: wait for 200-day reclaim",IF(J32>V32,"ABOVE ZONE: extended, wait",IF(IF(ISNUMBER(Q32),AND(Q32>Inputs!$B$5,Q32-Inputs!$B$5<=Inputs!$B$16),FALSE),"IN ZONE: earnings soon, wait",IF(N(M32)<=J32,"IN ZONE: analysts see no upside",IF(J32<=W32,"IN ZONE: at/below buy target - research","IN ZONE: research"))))))) | AD32: =IFERROR(INDEX('Rank Calc'!$P$5:$P$53,MATCH($A32,'Rank Calc'!$A$5:$A$53,0)),"") | AE32: AI networking. Fell ~18% from its 10/9 record on AI-debt worries. Still tied to AI capex like the chip names.
A33: UNP | B33: Union Pacific | C33: New industry | E33: A | G33: Railroad | H33: RICH -11% (high) | I33: AT RISK | J33: 301.93 | K33: 287.39 | L33: 269.98 | M33: 334.65 | N33: 19 | O33: 8 | P33: 1 | Q33: n/a | S33: =J33/L33-1 | T33: =J33/K33-1 | U33: =L33*(1+Inputs!$B$17) | V33: =L33*(1+Inputs!$B$18) | W33: =L33*(1+Inputs!$B$19) | X33: =J33/W33-1 | Y33: =IF(N(M33)>0,M33/W33-1,"") | Z33: =U33 | AA33: =IFERROR(IF(N(M33)>W33,(M33-W33)/(W33-Z33),""),"") | AB33: =IFERROR(N33/(N33+O33+P33),"") | AC33: =IF(D33="HELD","HELD: see Holdings sheet",IF(IF(ISNUMBER(R33),Inputs!$B$5<R33,FALSE),"WASH-SALE LOCK until "&TEXT(R33,"m/d"),IF(J33<U33,"BELOW ZONE: wait for 200-day reclaim",IF(J33>V33,"ABOVE ZONE: extended, wait",IF(IF(ISNUMBER(Q33),AND(Q33>Inputs!$B$5,Q33-Inputs!$B$5<=Inputs!$B$16),FALSE),"IN ZONE: earnings soon, wait",IF(N(M33)<=J33,"IN ZONE: analysts see no upside",IF(J33<=W33,"IN ZONE: at/below buy target - research","IN ZONE: research"))))))) | AD33: =IFERROR(INDEX('Rank Calc'!$P$5:$P$53,MATCH($A33,'Rank Calc'!$A$5:$A$53,0)),"") | AE33: Railroad. Norfolk Southern merger under STB review, close expected 2H 2027. Disruption quant flags AT RISK: check why.
A34: VRTX | B34: Vertex Pharmaceuticals | C34: New industry | E34: A | G34: Biotech | H34: RICH -12% (high) | I34: INNOVATING | J34: 540 | K34: 522.64 | L34: 478.62 | M34: 575.96 | N34: 27 | O34: 6 | P34: 2 | Q34: 46328 | S34: =J34/L34-1 | T34: =J34/K34-1 | U34: =L34*(1+Inputs!$B$17) | V34: =L34*(1+Inputs!$B$18) | W34: =L34*(1+Inputs!$B$19) | X34: =J34/W34-1 | Y34: =IF(N(M34)>0,M34/W34-1,"") | Z34: =U34 | AA34: =IFERROR(IF(N(M34)>W34,(M34-W34)/(W34-Z34),""),"") | AB34: =IFERROR(N34/(N34+O34+P34),"") | AC34: =IF(D34="HELD","HELD: see Holdings sheet",IF(IF(ISNUMBER(R34),Inputs!$B$5<R34,FALSE),"WASH-SALE LOCK until "&TEXT(R34,"m/d"),IF(J34<U34,"BELOW ZONE: wait for 200-day reclaim",IF(J34>V34,"ABOVE ZONE: extended, wait",IF(IF(ISNUMBER(Q34),AND(Q34>Inputs!$B$5,Q34-Inputs!$B$5<=Inputs!$B$16),FALSE),"IN ZONE: earnings soon, wait",IF(N(M34)<=J34,"IN ZONE: analysts see no upside",IF(J34<=W34,"IN ZONE: at/below buy target - research","IN ZONE: research"))))))) | AD34: =IFERROR(INDEX('Rank Calc'!$P$5:$P$53,MATCH($A34,'Rank Calc'!$A$5:$A$53,0)),"") | AE34: Biotech. Cystic fibrosis franchise; $10B Crinetics deal pending.
A35: CPAY | B35: Corpay | C35: New industry | E35: A | G35: Payments | H35: n/a | I35: n/a | J35: 397.97 | K35: 403.45 | L35: 355.07 | M35: 458.81 | N35: 16 | O35: 4 | P35: 0 | Q35: 46330 | S35: =J35/L35-1 | T35: =J35/K35-1 | U35: =L35*(1+Inputs!$B$17) | V35: =L35*(1+Inputs!$B$18) | W35: =L35*(1+Inputs!$B$19) | X35: =J35/W35-1 | Y35: =IF(N(M35)>0,M35/W35-1,"") | Z35: =U35 | AA35: =IFERROR(IF(N(M35)>W35,(M35-W35)/(W35-Z35),""),"") | AB35: =IFERROR(N35/(N35+O35+P35),"") | AC35: =IF(D35="HELD","HELD: see Holdings sheet",IF(IF(ISNUMBER(R35),Inputs!$B$5<R35,FALSE),"WASH-SALE LOCK until "&TEXT(R35,"m/d"),IF(J35<U35,"BELOW ZONE: wait for 200-day reclaim",IF(J35>V35,"ABOVE ZONE: extended, wait",IF(IF(ISNUMBER(Q35),AND(Q35>Inputs!$B$5,Q35-Inputs!$B$5<=Inputs!$B$16),FALSE),"IN ZONE: earnings soon, wait",IF(N(M35)<=J35,"IN ZONE: analysts see no upside",IF(J35<=W35,"IN ZONE: at/below buy target - research","IN ZONE: research"))))))) | AD35: =IFERROR(INDEX('Rank Calc'!$P$5:$P$53,MATCH($A35,'Rank Calc'!$A$5:$A$53,0)),"") | AE35: Payments. Rev +21%, raised 2026 guidance in Aug.
A36: AFRM | B36: Affirm | C36: New industry | E36: A+ | G36: Payments / BNPL | H36: n/a | I36: DISRUPTOR | J36: 74.84 | K36: 73.08 | L36: 66.51 | M36: 99.18 | N36: 32 | O36: 7 | P36: 0 | Q36: 46331 | R36: 46340 | S36: =J36/L36-1 | T36: =J36/K36-1 | U36: =L36*(1+Inputs!$B$17) | V36: =L36*(1+Inputs!$B$18) | W36: =L36*(1+Inputs!$B$19) | X36: =J36/W36-1 | Y36: =IF(N(M36)>0,M36/W36-1,"") | Z36: =U36 | AA36: =IFERROR(IF(N(M36)>W36,(M36-W36)/(W36-Z36),""),"") | AB36: =IFERROR(N36/(N36+O36+P36),"") | AC36: =IF(D36="HELD","HELD: see Holdings sheet",IF(IF(ISNUMBER(R36),Inputs!$B$5<R36,FALSE),"WASH-SALE LOCK until "&TEXT(R36,"m/d"),IF(J36<U36,"BELOW ZONE: wait for 200-day reclaim",IF(J36>V36,"ABOVE ZONE: extended, wait",IF(IF(ISNUMBER(Q36),AND(Q36>Inputs!$B$5,Q36-Inputs!$B$5<=Inputs!$B$16),FALSE),"IN ZONE: earnings soon, wait",IF(N(M36)<=J36,"IN ZONE: analysts see no upside",IF(J36<=W36,"IN ZONE: at/below buy target - research","IN ZONE: research"))))))) | AD36: =IFERROR(INDEX('Rank Calc'!$P$5:$P$53,MATCH($A36,'Rank Calc'!$A$5:$A$53,0)),"") | AE36: Payments / BNPL. Sold at a loss 10/14: wash-sale lock to 11/14. Missed EPS the last 3 quarters.
A37: AAPL | B37: Apple | C37: New industry | E37: A | G37: Consumer tech | H37: EXPENSIVE -36% (high) | I37: INNOVATING | J37: 348.91 | K37: 332.27 | L37: 296.11 | M37: 334.65 | N37: 27 | O37: 14 | P37: 6 | Q37: 46328 | S37: =J37/L37-1 | T37: =J37/K37-1 | U37: =L37*(1+Inputs!$B$17) | V37: =L37*(1+Inputs!$B$18) | W37: =L37*(1+Inputs!$B$19) | X37: =J37/W37-1 | Y37: =IF(N(M37)>0,M37/W37-1,"") | Z37: =U37 | AA37: =IFERROR(IF(N(M37)>W37,(M37-W37)/(W37-Z37),""),"") | AB37: =IFERROR(N37/(N37+O37+P37),"") | AC37: =IF(D37="HELD","HELD: see Holdings sheet",IF(IF(ISNUMBER(R37),Inputs!$B$5<R37,FALSE),"WASH-SALE LOCK until "&TEXT(R37,"m/d"),IF(J37<U37,"BELOW ZONE: wait for 200-day reclaim",IF(J37>V37,"ABOVE ZONE: extended, wait",IF(IF(ISNUMBER(Q37),AND(Q37>Inputs!$B$5,Q37-Inputs!$B$5<=Inputs!$B$16),FALSE),"IN ZONE: earnings soon, wait",IF(N(M37)<=J37,"IN ZONE: analysts see no upside",IF(J37<=W37,"IN ZONE: at/below buy target - research","IN ZONE: research"))))))) | AD37: =IFERROR(INDEX('Rank Calc'!$P$5:$P$53,MATCH($A37,'Rank Calc'!$A$5:$A$53,0)),"") | AE37: Consumer tech. Analyst mean target is BELOW price.
A38: MA | B38: Mastercard | C38: New industry | E38: A | G38: Payments | H38: FAIR +4% (high) | I38: STABLE | J38: 635.7 | K38: 584.94 | L38: 535.15 | M38: 695.83 | N38: 39 | O38: 4 | P38: 1 | Q38: n/a | S38: =J38/L38-1 | T38: =J38/K38-1 | U38: =L38*(1+Inputs!$B$17) | V38: =L38*(1+Inputs!$B$18) | W38: =L38*(1+Inputs!$B$19) | X38: =J38/W38-1 | Y38: =IF(N(M38)>0,M38/W38-1,"") | Z38: =U38 | AA38: =IFERROR(IF(N(M38)>W38,(M38-W38)/(W38-Z38),""),"") | AB38: =IFERROR(N38/(N38+O38+P38),"") | AC38: =IF(D38="HELD","HELD: see Holdings sheet",IF(IF(ISNUMBER(R38),Inputs!$B$5<R38,FALSE),"WASH-SALE LOCK until "&TEXT(R38,"m/d"),IF(J38<U38,"BELOW ZONE: wait for 200-day reclaim",IF(J38>V38,"ABOVE ZONE: extended, wait",IF(IF(ISNUMBER(Q38),AND(Q38>Inputs!$B$5,Q38-Inputs!$B$5<=Inputs!$B$16),FALSE),"IN ZONE: earnings soon, wait",IF(N(M38)<=J38,"IN ZONE: analysts see no upside",IF(J38<=W38,"IN ZONE: at/below buy target - research","IN ZONE: research"))))))) | AD38: =IFERROR(INDEX('Rank Calc'!$P$5:$P$53,MATCH($A38,'Rank Calc'!$A$5:$A$53,0)),"") | AE38: Payments. Q3 beat (adj EPS $5.31 vs $5.15, rev +14%). Near record high: 19% above its 200-day.
A40: COUNT | AC40: =COUNTIF(AC5:AC38,"IN ZONE*")&" in zone, "&COUNTIF(AC5:AC38,"BELOW*")&" below, "&COUNTIF(AC5:AC38,"ABOVE*")&" above"

Sheet Inputs
A1: Joint Portfolio Tracker - Assumptions
A2: Blue on yellow = input. Change any of these and the Holdings sheet recalculates.
A4: Assumption | B4: Value | C4: What it does
A5: As-of date (prices) | B5: 46324 | C5: Date of the prices in the Price column (see the Holdings header).
A6: Price to use | B6: Price | C6: Price or After-hours. After-hours falls back to Price when blank.
A7: Trim 1 trigger (% of final target) | B7: 1 | C7: Sell target 1 = final target x this. 100% = sell at the target.
A8: Trim 2 stretch above target | B8: 0.15 | C8: Sell target 2 = final target x (1 + this).
A9: Shares sold at each trim | B9: 0.33333333 | C9: Fraction of the position sold at T1 and again at T2. Last third rides the trail.
A10: Support buffer below 60-day low | B10: 0.01 | C10: Review level sits this far under the 60-day low.
A11: Max loss from cost - stocks | B11: 0.25 | C11: Review level never sits lower than cost x (1 - this).
A12: Max loss from cost - leveraged ETFs | B12: 0.3 | C12: Same, for 2x/3x ETFs.
A13: Trailing stop % | B13: 0.15 | C13: Trail = 60-day high x (1 - this), floored at cost, once price >= cost / (1 - this).
A14: Position cap - stocks (% of portfolio) | B14: 0.15 | C14: Flags OVERWEIGHT above this.
A15: Position cap - leveraged ETFs | B15: 0.05 | C15: Leveraged ETFs lose value in choppy markets; keep them small.
A16: Earnings warning window (days) | B16: 7 | C16: Flags a holding reporting within this many days.
A17: Watchlist: buy zone low vs 200-day | B17: -0.08 | C17: Bottom of the buy zone. Below it the 200-day has failed: wait for a reclaim.
A18: Watchlist: buy zone high vs 200-day | B18: 0.05 | C18: Top of the buy zone. Above it the name is extended: wait.
... A24: Rank: setup score when not scored | B24: 50 | C24: Neutral value for a name with no chart-setup score yet.

Sheet Rank Calc
A1: Rank Calc - every number here is a formula except the blue setup score
A2: Score = growth weight x percentile of upside + entry weight x percentile of reward:risk at today's price + timing weight x pre-breakout score/100, x (1 - penalty) when target agreement is LOW.
A4: Symbol | B4: Source | C4: Price | D4: Target | E4: Review Level | F4: Agreement | G4: Setup Score | H4: Status | I4: Upside | J4: Room to Review | K4: Reward : Risk | L4: Growth pct | M4: Entry pct | N4: Timing | O4: SCORE | P4: RANK
A5: META | B5: Held | C5: =Holdings!V6 | D5: =Holdings!Q6 | E5: =Holdings!AK6 | F5: =Holdings!R6 | G5: 29 | H5: =Holdings!AO6 | I5: =IFERROR(D5/C5-1,0) | J5: =IFERROR(1-E5/C5,0) | K5: =IF(J5<=0,0,MAX(I5,0)/J5) | L5: =IFERROR(PERCENTRANK($I$5:$I$53,I5),0) | M5: =IFERROR(PERCENTRANK($K$5:$K$53,K5),0) | N5: =IF(ISNUMBER(G5),G5,Inputs!$B$24)/100 | O5: =100*(Inputs!$B$20*L5+Inputs!$B$21*M5+Inputs!$B$22*N5)*IF(F5="LOW",1-Inputs!$B$23,1) | P5: =RANK(O5,$O$5:$O$53)
A6: AMZN | B6: Held | C6: =Holdings!V7 | D6: =Holdings!Q7 | E6: =Holdings!AK7 | F6: =Holdings!R7 | G6: 57 | H6: =Holdings!AO7 | I6: =IFERROR(D6/C6-1,0) | J6: =IFERROR(1-E6/C6,0) | K6: =IF(J6<=0,0,MAX(I6,0)/J6) | L6: =IFERROR(PERCENTRANK($I$5:$I$53,I6),0) | M6: =IFERROR(PERCENTRANK($K$5:$K$53,K6),0) | N6: =IF(ISNUMBER(G6),G6,Inputs!$B$24)/100 | O6: =100*(Inputs!$B$20*L6+Inputs!$B$21*M6+Inputs!$B$22*N6)*IF(F6="LOW",1-Inputs!$B$23,1) | P6: =RANK(O6,$O$5:$O$53)+COUNTIF($O$5:O5,O6)
A7: SOXL | B7: Held | C7: =Holdings!V8 | D7: =Holdings!Q8 | E7: =Holdings!AK8 | F7: =Holdings!R8 | G7: 57 | H7: =Holdings!AO8 | I7: =IFERROR(D7/C7-1,0) | J7: =IFERROR(1-E7/C7,0) | K7: =IF(J7<=0,0,MAX(I7,0)/J7) | L7: =IFERROR(PERCENTRANK($I$5:$I$53,I7),0) | M7: =IFERROR(PERCENTRANK($K$5:$K$53,K7),0) | N7: =IF(ISNUMBER(G7),G7,Inputs!$B$24)/100 | O7: =100*(Inputs!$B$20*L7+Inputs!$B$21*M7+Inputs!$B$22*N7)*IF(F7="LOW",1-Inputs!$B$23,1) | P7: =RANK(O7,$O$5:$O$53)+COUNTIF($O$5:O6,O7)
A8: SPCX | B8: Held | C8: =Holdings!V9 | D8: =Holdings!Q9 | E8: =Holdings!AK9 | F8: =Holdings!R9 | G8: n/a | H8: =Holdings!AO9 | I8: =IFERROR(D8/C8-1,0) | J8: =IFERROR(1-E8/C8,0) | K8: =IF(J8<=0,0,MAX(I8,0)/J8) | L8: =IFERROR(PERCENTRANK($I$5:$I$53,I8),0) | M8: =IFERROR(PERCENTRANK($K$5:$K$53,K8),0) | N8: =IF(ISNUMBER(G8),G8,Inputs!$B$24)/100 | O8: =100*(Inputs!$B$20*L8+Inputs!$B$21*M8+Inputs!$B$22*N8)*IF(F8="LOW",1-Inputs!$B$23,1) | P8: =RANK(O8,$O$5:$O$53)+COUNTIF($O$5:O7,O8)
A9: NBIS | B9: Held | C9: =Holdings!V10 | D9: =Holdings!Q10 | E9: =Holdings!AK10 | F9: =Holdings!R10 | G9: 43 | H9: =Holdings!AO10 | I9: =IFERROR(D9/C9-1,0) | J9: =IFERROR(1-E9/C9,0) | K9: =IF(J9<=0,0,MAX(I9,0)/J9) | L9: =IFERROR(PERCENTRANK($I$5:$I$53,I9),0) | M9: =IFERROR(PERCENTRANK($K$5:$K$53,K9),0) | N9: =IF(ISNUMBER(G9),G9,Inputs!$B$24)/100 | O9: =100*(Inputs!$B$20*L9+Inputs!$B$21*M9+Inputs!$B$22*N9)*IF(F9="LOW",1-Inputs!$B$23,1) | P9: =RANK(O9,$O$5:$O$53)+COUNTIF($O$5:O8,O9)
A10: MPWR | B10: Held | C10: =Holdings!V11 | D10: =Holdings!Q11 | E10: =Holdings!AK11 | F10: =Holdings!R11 | G10: 29 | H10: =Holdings!AO11 | I10: =IFERROR(D10/C10-1,0) | J10: =IFERROR(1-E10/C10,0) | K10: =IF(J10<=0,0,MAX(I10,0)/J10) | L10: =IFERROR(PERCENTRANK($I$5:$I$53,I10),0) | M10: =IFERROR(PERCENTRANK($K$5:$K$53,K10),0) | N10: =IF(ISNUMBER(G10),G10,Inputs!$B$24)/100 | O10: =100*(Inputs!$B$20*L10+Inputs!$B$21*M10+Inputs!$B$22*N10)*IF(F10="LOW",1-Inputs!$B$23,1) | P10: =RANK(O10,$O$5:$O$53)+COUNTIF($O$5:O9,O10)
A11: CDNS | B11: Held | C11: =Holdings!V12 | D11: =Holdings!Q12 | E11: =Holdings!AK12 | F11: =Holdings!R12 | G11: 29 | H11: =Holdings!AO12 | I11: =IFERROR(D11/C11-1,0) | J11: =IFERROR(1-E11/C11,0) | K11: =IF(J11<=0,0,MAX(I11,0)/J11) | L11: =IFERROR(PERCENTRANK($I$5:$I$53,I11),0) | M11: =IFERROR(PERCENTRANK($K$5:$K$53,K11),0) | N11: =IF(ISNUMBER(G11),G11,Inputs!$B$24)/100 | O11: =100*(Inputs!$B$20*L11+Inputs!$B$21*M11+Inputs!$B$22*N11)*IF(F11="LOW",1-Inputs!$B$23,1) | P11: =RANK(O11,$O$5:$O$53)+COUNTIF($O$5:O10,O11)
A12: NOW | B12: Held | C12: =Holdings!V13 | D12: =Holdings!Q13 | E12: =Holdings!AK13 | F12: =Holdings!R13 | G12: 57 | H12: =Holdings!AO13 | I12: =IFERROR(D12/C12-1,0) | J12: =IFERROR(1-E12/C12,0) | K12: =IF(J12<=0,0,MAX(I12,0)/J12) | L12: =IFERROR(PERCENTRANK($I$5:$I$53,I12),0) | M12: =IFERROR(PERCENTRANK($K$5:$K$53,K12),0) | N12: =IF(ISNUMBER(G12),G12,Inputs!$B$24)/100 | O12: =100*(Inputs!$B$20*L12+Inputs!$B$21*M12+Inputs!$B$22*N12)*IF(F12="LOW",1-Inputs!$B$23,1) | P12: =RANK(O12,$O$5:$O$53)+COUNTIF($O$5:O11,O12)
A13: ASND | B13: Held | C13: =Holdings!V14 | D13: =Holdings!Q14 | E13: =Holdings!AK14 | F13: =Holdings!R14 | G13: 14 | H13: =Holdings!AO14 | I13: =IFERROR(D13/C13-1,0) | J13: =IFERROR(1-E13/C13,0) | K13: =IF(J13<=0,0,MAX(I13,0)/J13) | L13: =IFERROR(PERCENTRANK($I$5:$I$53,I13),0) | M13: =IFERROR(PERCENTRANK($K$5:$K$53,K13),0) | N13: =IF(ISNUMBER(G13),G13,Inputs!$B$24)/100 | O13: =100*(Inputs!$B$20*L13+Inputs!$B$21*M13+Inputs!$B$22*N13)*IF(F13="LOW",1-Inputs!$B$23,1) | P13: =RANK(O13,$O$5:$O$53)+COUNTIF($O$5:O12,O13)
A14: VST | B14: Held | C14: =Holdings!V15 | D14: =Holdings!Q15 | E14: =Holdings!AK15 | F14: =Holdings!R15 | G14: 43 | H14: =Holdings!AO15 | I14: =IFERROR(D14/C14-1,0) | J14: =IFERROR(1-E14/C14,0) | K14: =IF(J14<=0,0,MAX(I14,0)/J14) | L14: =IFERROR(PERCENTRANK($I$5:$I$53,I14),0) | M14: =IFERROR(PERCENTRANK($K$5:$K$53,K14),0) | N14: =IF(ISNUMBER(G14),G14,Inputs!$B$24)/100 | O14: =100*(Inputs!$B$20*L14+Inputs!$B$21*M14+Inputs!$B$22*N14)*IF(F14="LOW",1-Inputs!$B$23,1) | P14: =RANK(O14,$O$5:$O$53)+COUNTIF($O$5:O13,O14)
A15: CRDO | B15: Held | C15: =Holdings!V16 | D15: =Holdings!Q16 | E15: =Holdings!AK16 | F15: =Holdings!R16 | G15: 43 | H15: =Holdings!AO16 | I15: =IFERROR(D15/C15-1,0) | J15: =IFERROR(1-E15/C15,0) | K15: =IF(J15<=0,0,MAX(I15,0)/J15) | L15: =IFERROR(PERCENTRANK($I$5:$I$53,I15),0) | M15: =IFERROR(PERCENTRANK($K$5:$K$53,K15),0) | N15: =IF(ISNUMBER(G15),G15,Inputs!$B$24)/100 | O15: =100*(Inputs!$B$20*L15+Inputs!$B$21*M15+Inputs!$B$22*N15)*IF(F15="LOW",1-Inputs!$B$23,1) | P15: =RANK(O15,$O$5:$O$53)+COUNTIF($O$5:O14,O15)
A16: SNDK | B16: Held | C16: =Holdings!V17 | D16: =Holdings!Q17 | E16: =Holdings!AK17 | F16: =Holdings!R17 | G16: 57 | H16: =Holdings!AO17 | I16: =IFERROR(D16/C16-1,0) | J16: =IFERROR(1-E16/C16,0) | K16: =IF(J16<=0,0,MAX(I16,0)/J16) | L16: =IFERROR(PERCENTRANK($I$5:$I$53,I16),0) | M16: =IFERROR(PERCENTRANK($K$5:$K$53,K16),0) | N16: =IF(ISNUMBER(G16),G16,Inputs!$B$24)/100 | O16: =100*(Inputs!$B$20*L16+Inputs!$B$21*M16+Inputs!$B$22*N16)*IF(F16="LOW",1-Inputs!$B$23,1) | P16: =RANK(O16,$O$5:$O$53)+COUNTIF($O$5:O15,O16)
A17: OKLO | B17: Held | C17: =Holdings!V18 | D17: =Holdings!Q18 | E17: =Holdings!AK18 | F17: =Holdings!R18 | G17: 86 | H17: =Holdings!AO18 | I17: =IFERROR(D17/C17-1,0) | J17: =IFERROR(1-E17/C17,0) | K17: =IF(J17<=0,0,MAX(I17,0)/J17) | L17: =IFERROR(PERCENTRANK($I$5:$I$53,I17),0) | M17: =IFERROR(PERCENTRANK($K$5:$K$53,K17),0) | N17: =IF(ISNUMBER(G17),G17,Inputs!$B$24)/100 | O17: =100*(Inputs!$B$20*L17+Inputs!$B$21*M17+Inputs!$B$22*N17)*IF(F17="LOW",1-Inputs!$B$23,1) | P17: =RANK(O17,$O$5:$O$53)+COUNTIF($O$5:O16,O17)
A18: AAOX | B18: Held | C18: =Holdings!V19 | D18: =Holdings!Q19 | E18: =Holdings!AK19 | F18: =Holdings!R19 | G18: 43 | H18: =Holdings!AO19 | I18: =IFERROR(D18/C18-1,0) | J18: =IFERROR(1-E18/C18,0) | K18: =IF(J18<=0,0,MAX(I18,0)/J18) | L18: =IFERROR(PERCENTRANK($I$5:$I$53,I18),0) | M18: =IFERROR(PERCENTRANK($K$5:$K$53,K18),0) | N18: =IF(ISNUMBER(G18),G18,Inputs!$B$24)/100 | O18: =100*(Inputs!$B$20*L18+Inputs!$B$21*M18+Inputs!$B$22*N18)*IF(F18="LOW",1-Inputs!$B$23,1) | P18: =RANK(O18,$O$5:$O$53)+COUNTIF($O$5:O17,O18)
A19: GOOGL | B19: Held | C19: =Holdings!V20 | D19: =Holdings!Q20 | E19: =Holdings!AK20 | F19: =Holdings!R20 | G19: 57 | H19: =Holdings!AO20 | I19: =IFERROR(D19/C19-1,0) | J19: =IFERROR(1-E19/C19,0) | K19: =IF(J19<=0,0,MAX(I19,0)/J19) | L19: =IFERROR(PERCENTRANK($I$5:$I$53,I19),0) | M19: =IFERROR(PERCENTRANK($K$5:$K$53,K19),0) | N19: =IF(ISNUMBER(G19),G19,Inputs!$B$24)/100 | O19: =100*(Inputs!$B$20*L19+Inputs!$B$21*M19+Inputs!$B$22*N19)*IF(F19="LOW",1-Inputs!$B$23,1) | P19: =RANK(O19,$O$5:$O$53)+COUNTIF($O$5:O18,O19)
A20: IONQ | B20: Held | C20: =Holdings!V21 | D20: =Holdings!Q21 | E20: =Holdings!AK21 | F20: =Holdings!R21 | G20: 86 | H20: =Holdings!AO21 | I20: =IFERROR(D20/C20-1,0) | J20: =IFERROR(1-E20/C20,0) | K20: =IF(J20<=0,0,MAX(I20,0)/J20) | L20: =IFERROR(PERCENTRANK($I$5:$I$53,I20),0) | M20: =IFERROR(PERCENTRANK($K$5:$K$53,K20),0) | N20: =IF(ISNUMBER(G20),G20,Inputs!$B$24)/100 | O20: =100*(Inputs!$B$20*L20+Inputs!$B$21*M20+Inputs!$B$22*N20)*IF(F20="LOW",1-Inputs!$B$23,1) | P20: =RANK(O20,$O$5:$O$53)+COUNTIF($O$5:O19,O20)
A21: AUR | B21: Held | C21: =Holdings!V22 | D21: =Holdings!Q22 | E21: =Holdings!AK22 | F21: =Holdings!R22 | G21: 71 | H21: =Holdings!AO22 | I21: =IFERROR(D21/C21-1,0) | J21: =IFERROR(1-E21/C21,0) | K21: =IF(J21<=0,0,MAX(I21,0)/J21) | L21: =IFERROR(PERCENTRANK($I$5:$I$53,I21),0) | M21: =IFERROR(PERCENTRANK($K$5:$K$53,K21),0) | N21: =IF(ISNUMBER(G21),G21,Inputs!$B$24)/100 | O21: =100*(Inputs!$B$20*L21+Inputs!$B$21*M21+Inputs!$B$22*N21)*IF(F21="LOW",1-Inputs!$B$23,1) | P21: =RANK(O21,$O$5:$O$53)+COUNTIF($O$5:O20,O21)
A22: AEM | B22: Buy Zone | C22: =Watchlist!J5 | D22: =Watchlist!M5 | E22: =Watchlist!U5 | F22: analyst mean | G22: 86 | H22: =Watchlist!AC5 | I22: =IFERROR(D22/C22-1,0) | J22: =IFERROR(1-E22/C22,0) | K22: =IF(J22<=0,0,MAX(I22,0)/J22) | L22: =IFERROR(PERCENTRANK($I$5:$I$53,I22),0) | M22: =IFERROR(PERCENTRANK($K$5:$K$53,K22),0) | N22: =IF(ISNUMBER(G22),G22,Inputs!$B$24)/100 | O22: =100*(Inputs!$B$20*L22+Inputs!$B$21*M22+Inputs!$B$22*N22)*IF(F22="LOW",1-Inputs!$B$23,1) | P22: =RANK(O22,$O$5:$O$53)+COUNTIF($O$5:O21,O22)
A23: NVDA | B23: Buy Zone | C23: =Watchlist!J6 | D23: =Watchlist!M6 | E23: =Watchlist!U6 | F23: analyst mean | G23: 71 | H23: =Watchlist!AC6 | I23: =IFERROR(D23/C23-1,0) | J23: =IFERROR(1-E23/C23,0) | K23: =IF(J23<=0,0,MAX(I23,0)/J23) | L23: =IFERROR(PERCENTRANK($I$5:$I$53,I23),0) | M23: =IFERROR(PERCENTRANK($K$5:$K$53,K23),0) | N23: =IF(ISNUMBER(G23),G23,Inputs!$B$24)/100 | O23: =100*(Inputs!$B$20*L23+Inputs!$B$21*M23+Inputs!$B$22*N23)*IF(F23="LOW",1-Inputs!$B$23,1) | P23: =RANK(O23,$O$5:$O$53)+COUNTIF($O$5:O22,O23)
A24: STX | B24: Buy Zone | C24: =Watchlist!J7 | D24: =Watchlist!M7 | E24: =Watchlist!U7 | F24: analyst mean | G24: 71 | H24: =Watchlist!AC7 | I24: =IFERROR(D24/C24-1,0) | J24: =IFERROR(1-E24/C24,0) | K24: =IF(J24<=0,0,MAX(I24,0)/J24) | L24: =IFERROR(PERCENTRANK($I$5:$I$53,I24),0) | M24: =IFERROR(PERCENTRANK($K$5:$K$53,K24),0) | N24: =IF(ISNUMBER(G24),G24,Inputs!$B$24)/100 | O24: =100*(Inputs!$B$20*L24+Inputs!$B$21*M24+Inputs!$B$22*N24)*IF(F24="LOW",1-Inputs!$B$23,1) | P24: =RANK(O24,$O$5:$O$53)+COUNTIF($O$5:O23,O24)
A25: SCCO | B25: Buy Zone | C25: =Watchlist!J8 | D25: =Watchlist!M8 | E25: =Watchlist!U8 | F25: analyst mean | G25: 71 | H25: =Watchlist!AC8 | I25: =IFERROR(D25/C25-1,0) | J25: =IFERROR(1-E25/C25,0) | K25: =IF(J25<=0,0,MAX(I25,0)/J25) | L25: =IFERROR(PERCENTRANK($I$5:$I$53,I25),0) | M25: =IFERROR(PERCENTRANK($K$5:$K$53,K25),0) | N25: =IF(ISNUMBER(G25),G25,Inputs!$B$24)/100 | O25: =100*(Inputs!$B$20*L25+Inputs!$B$21*M25+Inputs!$B$22*N25)*IF(F25="LOW",1-Inputs!$B$23,1) | P25: =RANK(O25,$O$5:$O$53)+COUNTIF($O$5:O24,O25)
A26: FNV | B26: Buy Zone | C26: =Watchlist!J9 | D26: =Watchlist!M9 | E26: =Watchlist!U9 | F26: analyst mean | G26: 71 | H26: =Watchlist!AC9 | I26: =IFERROR(D26/C26-1,0) | J26: =IFERROR(1-E26/C26,0) | K26: =IF(J26<=0,0,MAX(I26,0)/J26) | L26: =IFERROR(PERCENTRANK($I$5:$I$53,I26),0) | M26: =IFERROR(PERCENTRANK($K$5:$K$53,K26),0) | N26: =IF(ISNUMBER(G26),G26,Inputs!$B$24)/100 | O26: =100*(Inputs!$B$20*L26+Inputs!$B$21*M26+Inputs!$B$22*N26)*IF(F26="LOW",1-Inputs!$B$23,1) | P26: =RANK(O26,$O$5:$O$53)+COUNTIF($O$5:O25,O26)
A27: AVGO | B27: Buy Zone | C27: =Watchlist!J10 | D27: =Watchlist!M10 | E27: =Watchlist!U10 | F27: analyst mean | G27: 57 | H27: =Watchlist!AC10 | I27: =IFERROR(D27/C27-1,0) | J27: =IFERROR(1-E27/C27,0) | K27: =IF(J27<=0,0,MAX(I27,0)/J27) | L27: =IFERROR(PERCENTRANK($I$5:$I$53,I27),0) | M27: =IFERROR(PERCENTRANK($K$5:$K$53,K27),0) | N27: =IF(ISNUMBER(G27),G27,Inputs!$B$24)/100 | O27: =100*(Inputs!$B$20*L27+Inputs!$B$21*M27+Inputs!$B$22*N27)*IF(F27="LOW",1-Inputs!$B$23,1) | P27: =RANK(O27,$O$5:$O$53)+COUNTIF($O$5:O26,O27)
A28: HOOD | B28: Buy Zone | C28: =Watchlist!J11 | D28: =Watchlist!M11 | E28: =Watchlist!U11 | F28: analyst mean | G28: 57 | H28: =Watchlist!AC11 | I28: =IFERROR(D28/C28-1,0) | J28: =IFERROR(1-E28/C28,0) | K28: =IF(J28<=0,0,MAX(I28,0)/J28) | L28: =IFERROR(PERCENTRANK($I$5:$I$53,I28),0) | M28: =IFERROR(PERCENTRANK($K$5:$K$53,K28),0) | N28: =IF(ISNUMBER(G28),G28,Inputs!$B$24)/100 | O28: =100*(Inputs!$B$20*L28+Inputs!$B$21*M28+Inputs!$B$22*N28)*IF(F28="LOW",1-Inputs!$B$23,1) | P28: =RANK(O28,$O$5:$O$53)+COUNTIF($O$5:O27,O28)
A29: NEM | B29: Buy Zone | C29: =Watchlist!J12 | D29: =Watchlist!M12 | E29: =Watchlist!U12 | F29: analyst mean | G29: 57 | H29: =Watchlist!AC12 | I29: =IFERROR(D29/C29-1,0) | J29: =IFERROR(1-E29/C29,0) | K29: =IF(J29<=0,0,MAX(I29,0)/J29) | L29: =IFERROR(PERCENTRANK($I$5:$I$53,I29),0) | M29: =IFERROR(PERCENTRANK($K$5:$K$53,K29),0) | N29: =IF(ISNUMBER(G29),G29,Inputs!$B$24)/100 | O29: =100*(Inputs!$B$20*L29+Inputs!$B$21*M29+Inputs!$B$22*N29)*IF(F29="LOW",1-Inputs!$B$23,1) | P29: =RANK(O29,$O$5:$O$53)+COUNTIF($O$5:O28,O29)
A30: ASML | B30: Buy Zone | C30: =Watchlist!J13 | D30: =Watchlist!M13 | E30: =Watchlist!U13 | F30: analyst mean | G30: 43 | H30: =Watchlist!AC13 | I30: =IFERROR(D30/C30-1,0) | J30: =IFERROR(1-E30/C30,0) | K30: =IF(J30<=0,0,MAX(I30,0)/J30) | L30: =IFERROR(PERCENTRANK($I$5:$I$53,I30),0) | M30: =IFERROR(PERCENTRANK($K$5:$K$53,K30),0) | N30: =IF(ISNUMBER(G30),G30,Inputs!$B$24)/100 | O30: =100*(Inputs!$B$20*L30+Inputs!$B$21*M30+Inputs!$B$22*N30)*IF(F30="LOW",1-Inputs!$B$23,1) | P30: =RANK(O30,$O$5:$O$53)+COUNTIF($O$5:O29,O30)
A31: AMAT | B31: Buy Zone | C31: =Watchlist!J14 | D31: =Watchlist!M14 | E31: =Watchlist!U14 | F31: analyst mean | G31: 43 | H31: =Watchlist!AC14 | I31: =IFERROR(D31/C31-1,0) | J31: =IFERROR(1-E31/C31,0) | K31: =IF(J31<=0,0,MAX(I31,0)/J31) | L31: =IFERROR(PERCENTRANK($I$5:$I$53,I31),0) | M31: =IFERROR(PERCENTRANK($K$5:$K$53,K31),0) | N31: =IF(ISNUMBER(G31),G31,Inputs!$B$24)/100 | O31: =100*(Inputs!$B$20*L31+Inputs!$B$21*M31+Inputs!$B$22*N31)*IF(F31="LOW",1-Inputs!$B$23,1) | P31: =RANK(O31,$O$5:$O$53)+COUNTIF($O$5:O30,O31)
A32: KEYS | B32: Buy Zone | C32: =Watchlist!J15 | D32: =Watchlist!M15 | E32: =Watchlist!U15 | F32: analyst mean | G32: 43 | H32: =Watchlist!AC15 | I32: =IFERROR(D32/C32-1,0) | J32: =IFERROR(1-E32/C32,0) | K32: =IF(J32<=0,0,MAX(I32,0)/J32) | L32: =IFERROR(PERCENTRANK($I$5:$I$53,I32),0) | M32: =IFERROR(PERCENTRANK($K$5:$K$53,K32),0) | N32: =IF(ISNUMBER(G32),G32,Inputs!$B$24)/100 | O32: =100*(Inputs!$B$20*L32+Inputs!$B$21*M32+Inputs!$B$22*N32)*IF(F32="LOW",1-Inputs!$B$23,1) | P32: =RANK(O32,$O$5:$O$53)+COUNTIF($O$5:O31,O32)
A33: WES | B33: Buy Zone | C33: =Watchlist!J17 | D33: =Watchlist!M17 | E33: =Watchlist!U17 | F33: analyst mean | G33: 29 | H33: =Watchlist!AC17 | I33: =IFERROR(D33/C33-1,0) | J33: =IFERROR(1-E33/C33,0) | K33: =IF(J33<=0,0,MAX(I33,0)/J33) | L33: =IFERROR(PERCENTRANK($I$5:$I$53,I33),0) | M33: =IFERROR(PERCENTRANK($K$5:$K$53,K33),0) | N33: =IF(ISNUMBER(G33),G33,Inputs!$B$24)/100 | O33: =100*(Inputs!$B$20*L33+Inputs!$B$21*M33+Inputs!$B$22*N33)*IF(F33="LOW",1-Inputs!$B$23,1) | P33: =RANK(O33,$O$5:$O$53)+COUNTIF($O$5:O32,O33)
A34: RGLD | B34: Buy Zone | C34: =Watchlist!J18 | D34: =Watchlist!M18 | E34: =Watchlist!U18 | F34: analyst mean | G34: 29 | H34: =Watchlist!AC18 | I34: =IFERROR(D34/C34-1,0) | J34: =IFERROR(1-E34/C34,0) | K34: =IF(J34<=0,0,MAX(I34,0)/J34) | L34: =IFERROR(PERCENTRANK($I$5:$I$53,I34),0) | M34: =IFERROR(PERCENTRANK($K$5:$K$53,K34),0) | N34: =IF(ISNUMBER(G34),G34,Inputs!$B$24)/100 | O34: =100*(Inputs!$B$20*L34+Inputs!$B$21*M34+Inputs!$B$22*N34)*IF(F34="LOW",1-Inputs!$B$23,1) | P34: =RANK(O34,$O$5:$O$53)+COUNTIF($O$5:O33,O34)
A35: WDC | B35: Buy Zone | C35: =Watchlist!J19 | D35: =Watchlist!M19 | E35: =Watchlist!U19 | F35: analyst mean | G35: 29 | H35: =Watchlist!AC19 | I35: =IFERROR(D35/C35-1,0) | J35: =IFERROR(1-E35/C35,0) | K35: =IF(J35<=0,0,MAX(I35,0)/J35) | L35: =IFERROR(PERCENTRANK($I$5:$I$53,I35),0) | M35: =IFERROR(PERCENTRANK($K$5:$K$53,K35),0) | N35: =IF(ISNUMBER(G35),G35,Inputs!$B$24)/100 | O35: =100*(Inputs!$B$20*L35+Inputs!$B$21*M35+Inputs!$B$22*N35)*IF(F35="LOW",1-Inputs!$B$23,1) | P35: =RANK(O35,$O$5:$O$53)+COUNTIF($O$5:O34,O35)
A36: NBIX | B36: Buy Zone | C36: =Watchlist!J20 | D36: =Watchlist!M20 | E36: =Watchlist!U20 | F36: analyst mean | G36: 29 | H36: =Watchlist!AC20 | I36: =IFERROR(D36/C36-1,0) | J36: =IFERROR(1-E36/C36,0) | K36: =IF(J36<=0,0,MAX(I36,0)/J36) | L36: =IFERROR(PERCENTRANK($I$5:$I$53,I36),0) | M36: =IFERROR(PERCENTRANK($K$5:$K$53,K36),0) | N36: =IF(ISNUMBER(G36),G36,Inputs!$B$24)/100 | O36: =100*(Inputs!$B$20*L36+Inputs!$B$21*M36+Inputs!$B$22*N36)*IF(F36="LOW",1-Inputs!$B$23,1) | P36: =RANK(O36,$O$5:$O$53)+COUNTIF($O$5:O35,O36)
A37: ADBE | B37: Buy Zone | C37: =Watchlist!J22 | D37: =Watchlist!M22 | E37: =Watchlist!U22 | F37: analyst mean | G37: 29 | H37: =Watchlist!AC22 | I37: =IFERROR(D37/C37-1,0) | J37: =IFERROR(1-E37/C37,0) | K37: =IF(J37<=0,0,MAX(I37,0)/J37) | L37: =IFERROR(PERCENTRANK($I$5:$I$53,I37),0) | M37: =IFERROR(PERCENTRANK($K$5:$K$53,K37),0) | N37: =IF(ISNUMBER(G37),G37,Inputs!$B$24)/100 | O37: =100*(Inputs!$B$20*L37+Inputs!$B$21*M37+Inputs!$B$22*N37)*IF(F37="LOW",1-Inputs!$B$23,1) | P37: =RANK(O37,$O$5:$O$53)+COUNTIF($O$5:O36,O37)
A38: PAC | B38: Buy Zone | C38: =Watchlist!J23 | D38: =Watchlist!M23 | E38: =Watchlist!U23 | F38: analyst mean | G38: 0 | H38: =Watchlist!AC23 | I38: =IFERROR(D38/C38-1,0) | J38: =IFERROR(1-E38/C38,0) | K38: =IF(J38<=0,0,MAX(I38,0)/J38) | L38: =IFERROR(PERCENTRANK($I$5:$I$53,I38),0) | M38: =IFERROR(PERCENTRANK($K$5:$K$53,K38),0) | N38: =IF(ISNUMBER(G38),G38,Inputs!$B$24)/100 | O38: =100*(Inputs!$B$20*L38+Inputs!$B$21*M38+Inputs!$B$22*N38)*IF(F38="LOW",1-Inputs!$B$23,1) | P38: =RANK(O38,$O$5:$O$53)+COUNTIF($O$5:O37,O38)
A39: PSA | B39: Buy Zone | C39: =Watchlist!J24 | D39: =Watchlist!M24 | E39: =Watchlist!U24 | F39: analyst mean | G39: 0 | H39: =Watchlist!AC24 | I39: =IFERROR(D39/C39-1,0) | J39: =IFERROR(1-E39/C39,0) | K39: =IF(J39<=0,0,MAX(I39,0)/J39) | L39: =IFERROR(PERCENTRANK($I$5:$I$53,I39),0) | M39: =IFERROR(PERCENTRANK($K$5:$K$53,K39),0) | N39: =IF(ISNUMBER(G39),G39,Inputs!$B$24)/100 | O39: =100*(Inputs!$B$20*L39+Inputs!$B$21*M39+Inputs!$B$22*N39)*IF(F39="LOW",1-Inputs!$B$23,1) | P39: =RANK(O39,$O$5:$O$53)+COUNTIF($O$5:O38,O39)
A40: ISRG | B40: Buy Zone | C40: =Watchlist!J25 | D40: =Watchlist!M25 | E40: =Watchlist!U25 | F40: analyst mean | G40: 0 | H40: =Watchlist!AC25 | I40: =IFERROR(D40/C40-1,0) | J40: =IFERROR(1-E40/C40,0) | K40: =IF(J40<=0,0,MAX(I40,0)/J40) | L40: =IFERROR(PERCENTRANK($I$5:$I$53,I40),0) | M40: =IFERROR(PERCENTRANK($K$5:$K$53,K40),0) | N40: =IF(ISNUMBER(G40),G40,Inputs!$B$24)/100 | O40: =100*(Inputs!$B$20*L40+Inputs!$B$21*M40+Inputs!$B$22*N40)*IF(F40="LOW",1-Inputs!$B$23,1) | P40: =RANK(O40,$O$5:$O$53)+COUNTIF($O$5:O39,O40)
A41: TROW | B41: Buy Zone | C41: =Watchlist!J26 | D41: =Watchlist!M26 | E41: =Watchlist!U26 | F41: analyst mean | G41: 0 | H41: =Watchlist!AC26 | I41: =IFERROR(D41/C41-1,0) | J41: =IFERROR(1-E41/C41,0) | K41: =IF(J41<=0,0,MAX(I41,0)/J41) | L41: =IFERROR(PERCENTRANK($I$5:$I$53,I41),0) | M41: =IFERROR(PERCENTRANK($K$5:$K$53,K41),0) | N41: =IF(ISNUMBER(G41),G41,Inputs!$B$24)/100 | O41: =100*(Inputs!$B$20*L41+Inputs!$B$21*M41+Inputs!$B$22*N41)*IF(F41="LOW",1-Inputs!$B$23,1) | P41: =RANK(O41,$O$5:$O$53)+COUNTIF($O$5:O40,O41)
A42: SKHY | B42: Buy Zone | C42: =Watchlist!J27 | D42: =Watchlist!M27 | E42: =Watchlist!U27 | F42: analyst mean | G42: n/a | H42: =Watchlist!AC27 | I42: =IFERROR(D42/C42-1,0) | J42: =IFERROR(1-E42/C42,0) | K42: =IF(J42<=0,0,MAX(I42,0)/J42) | L42: =IFERROR(PERCENTRANK($I$5:$I$53,I42),0) | M42: =IFERROR(PERCENTRANK($K$5:$K$53,K42),0) | N42: =IF(ISNUMBER(G42),G42,Inputs!$B$24)/100 | O42: =100*(Inputs!$B$20*L42+Inputs!$B$21*M42+Inputs!$B$22*N42)*IF(F42="LOW",1-Inputs!$B$23,1) | P42: =RANK(O42,$O$5:$O$53)+COUNTIF($O$5:O41,O42)
A43: MOD | B43: Re-buy | C43: =Watchlist!J28 | D43: =Watchlist!M28 | E43: =Watchlist!U28 | F43: analyst mean | G43: n/a | H43: =Watchlist!AC28 | I43: =IFERROR(D43/C43-1,0) | J43: =IFERROR(1-E43/C43,0) | K43: =IF(J43<=0,0,MAX(I43,0)/J43) | L43: =IFERROR(PERCENTRANK($I$5:$I$53,I43),0) | M43: =IFERROR(PERCENTRANK($K$5:$K$53,K43),0) | N43: =IF(ISNUMBER(G43),G43,Inputs!$B$24)/100 | O43: =100*(Inputs!$B$20*L43+Inputs!$B$21*M43+Inputs!$B$22*N43)*IF(F43="LOW",1-Inputs!$B$23,1) | P43: =RANK(O43,$O$5:$O$53)+COUNTIF($O$5:O42,O43)
A44: SPG | B44: New industry | C44: =Watchlist!J29 | D44: =Watchlist!M29 | E44: =Watchlist!U29 | F44: analyst mean | G44: n/a | H44: =Watchlist!AC29 | I44: =IFERROR(D44/C44-1,0) | J44: =IFERROR(1-E44/C44,0) | K44: =IF(J44<=0,0,MAX(I44,0)/J44) | L44: =IFERROR(PERCENTRANK($I$5:$I$53,I44),0) | M44: =IFERROR(PERCENTRANK($K$5:$K$53,K44),0) | N44: =IF(ISNUMBER(G44),G44,Inputs!$B$24)/100 | O44: =100*(Inputs!$B$20*L44+Inputs!$B$21*M44+Inputs!$B$22*N44)*IF(F44="LOW",1-Inputs!$B$23,1) | P44: =RANK(O44,$O$5:$O$53)+COUNTIF($O$5:O43,O44)
A45: MNST | B45: New industry | C45: =Watchlist!J30 | D45: =Watchlist!M30 | E45: =Watchlist!U30 | F45: analyst mean | G45: n/a | H45: =Watchlist!AC30 | I45: =IFERROR(D45/C45-1,0) | J45: =IFERROR(1-E45/C45,0) | K45: =IF(J45<=0,0,MAX(I45,0)/J45) | L45: =IFERROR(PERCENTRANK($I$5:$I$53,I45),0) | M45: =IFERROR(PERCENTRANK($K$5:$K$53,K45),0) | N45: =IF(ISNUMBER(G45),G45,Inputs!$B$24)/100 | O45: =100*(Inputs!$B$20*L45+Inputs!$B$21*M45+Inputs!$B$22*N45)*IF(F45="LOW",1-Inputs!$B$23,1) | P45: =RANK(O45,$O$5:$O$53)+COUNTIF($O$5:O44,O45)
A46: INCY | B46: New industry | C46: =Watchlist!J31 | D46: =Watchlist!M31 | E46: =Watchlist!U31 | F46: analyst mean | G46: n/a | H46: =Watchlist!AC31 | I46: =IFERROR(D46/C46-1,0) | J46: =IFERROR(1-E46/C46,0) | K46: =IF(J46<=0,0,MAX(I46,0)/J46) | L46: =IFERROR(PERCENTRANK($I$5:$I$53,I46),0) | M46: =IFERROR(PERCENTRANK($K$5:$K$53,K46),0) | N46: =IF(ISNUMBER(G46),G46,Inputs!$B$24)/100 | O46: =100*(Inputs!$B$20*L46+Inputs!$B$21*M46+Inputs!$B$22*N46)*IF(F46="LOW",1-Inputs!$B$23,1) | P46: =RANK(O46,$O$5:$O$53)+COUNTIF($O$5:O45,O46)
A47: ANET | B47: New industry | C47: =Watchlist!J32 | D47: =Watchlist!M32 | E47: =Watchlist!U32 | F47: analyst mean | G47: n/a | H47: =Watchlist!AC32 | I47: =IFERROR(D47/C47-1,0) | J47: =IFERROR(1-E47/C47,0) | K47: =IF(J47<=0,0,MAX(I47,0)/J47) | L47: =IFERROR(PERCENTRANK($I$5:$I$53,I47),0) | M47: =IFERROR(PERCENTRANK($K$5:$K$53,K47),0) | N47: =IF(ISNUMBER(G47),G47,Inputs!$B$24)/100 | O47: =100*(Inputs!$B$20*L47+Inputs!$B$21*M47+Inputs!$B$22*N47)*IF(F47="LOW",1-Inputs!$B$23,1) | P47: =RANK(O47,$O$5:$O$53)+COUNTIF($O$5:O46,O47)
A48: UNP | B48: New industry | C48: =Watchlist!J33 | D48: =Watchlist!M33 | E48: =Watchlist!U33 | F48: analyst mean | G48: n/a | H48: =Watchlist!AC33 | I48: =IFERROR(D48/C48-1,0) | J48: =IFERROR(1-E48/C48,0) | K48: =IF(J48<=0,0,MAX(I48,0)/J48) | L48: =IFERROR(PERCENTRANK($I$5:$I$53,I48),0) | M48: =IFERROR(PERCENTRANK($K$5:$K$53,K48),0) | N48: =IF(ISNUMBER(G48),G48,Inputs!$B$24)/100 | O48: =100*(Inputs!$B$20*L48+Inputs!$B$21*M48+Inputs!$B$22*N48)*IF(F48="LOW",1-Inputs!$B$23,1) | P48: =RANK(O48,$O$5:$O$53)+COUNTIF($O$5:O47,O48)
A49: VRTX | B49: New industry | C49: =Watchlist!J34 | D49: =Watchlist!M34 | E49: =Watchlist!U34 | F49: analyst mean | G49: n/a | H49: =Watchlist!AC34 | I49: =IFERROR(D49/C49-1,0) | J49: =IFERROR(1-E49/C49,0) | K49: =IF(J49<=0,0,MAX(I49,0)/J49) | L49: =IFERROR(PERCENTRANK($I$5:$I$53,I49),0) | M49: =IFERROR(PERCENTRANK($K$5:$K$53,K49),0) | N49: =IF(ISNUMBER(G49),G49,Inputs!$B$24)/100 | O49: =100*(Inputs!$B$20*L49+Inputs!$B$21*M49+Inputs!$B$22*N49)*IF(F49="LOW",1-Inputs!$B$23,1) | P49: =RANK(O49,$O$5:$O$53)+COUNTIF($O$5:O48,O49)
A50: CPAY | B50: New industry | C50: =Watchlist!J35 | D50: =Watchlist!M35 | E50: =Watchlist!U35 | F50: analyst mean | G50: n/a | H50: =Watchlist!AC35 | I50: =IFERROR(D50/C50-1,0) | J50: =IFERROR(1-E50/C50,0) | K50: =IF(J50<=0,0,MAX(I50,0)/J50) | L50: =IFERROR(PERCENTRANK($I$5:$I$53,I50),0) | M50: =IFERROR(PERCENTRANK($K$5:$K$53,K50),0) | N50: =IF(ISNUMBER(G50),G50,Inputs!$B$24)/100 | O50: =100*(Inputs!$B$20*L50+Inputs!$B$21*M50+Inputs!$B$22*N50)*IF(F50="LOW",1-Inputs!$B$23,1) | P50: =RANK(O50,$O$5:$O$53)+COUNTIF($O$5:O49,O50)
A51: AFRM | B51: New industry | C51: =Watchlist!J36 | D51: =Watchlist!M36 | E51: =Watchlist!U36 | F51: analyst mean | G51: n/a | H51: =Watchlist!AC36 | I51: =IFERROR(D51/C51-1,0) | J51: =IFERROR(1-E51/C51,0) | K51: =IF(J51<=0,0,MAX(I51,0)/J51) | L51: =IFERROR(PERCENTRANK($I$5:$I$53,I51),0) | M51: =IFERROR(PERCENTRANK($K$5:$K$53,K51),0) | N51: =IF(ISNUMBER(G51),G51,Inputs!$B$24)/100 | O51: =100*(Inputs!$B$20*L51+Inputs!$B$21*M51+Inputs!$B$22*N51)*IF(F51="LOW",1-Inputs!$B$23,1) | P51: =RANK(O51,$O$5:$O$53)+COUNTIF($O$5:O50,O51)
A52: AAPL | B52: New industry | C52: =Watchlist!J37 | D52: =Watchlist!M37 | E52: =Watchlist!U37 | F52: analyst mean | G52: n/a | H52: =Watchlist!AC37 | I52: =IFERROR(D52/C52-1,0) | J52: =IFERROR(1-E52/C52,0) | K52: =IF(J52<=0,0,MAX(I52,0)/J52) | L52: =IFERROR(PERCENTRANK($I$5:$I$53,I52),0) | M52: =IFERROR(PERCENTRANK($K$5:$K$53,K52),0) | N52: =IF(ISNUMBER(G52),G52,Inputs!$B$24)/100 | O52: =100*(Inputs!$B$20*L52+Inputs!$B$21*M52+Inputs!$B$22*N52)*IF(F52="LOW",1-Inputs!$B$23,1) | P52: =RANK(O52,$O$5:$O$53)+COUNTIF($O$5:O51,O52)
A53: MA | B53: New industry | C53: =Watchlist!J38 | D53: =Watchlist!M38 | E53: =Watchlist!U38 | F53: analyst mean | G53: n/a | H53: =Watchlist!AC38 | I53: =IFERROR(D53/C53-1,0) | J53: =IFERROR(1-E53/C53,0) | K53: =IF(J53<=0,0,MAX(I53,0)/J53) | L53: =IFERROR(PERCENTRANK($I$5:$I$53,I53),0) | M53: =IFERROR(PERCENTRANK($K$5:$K$53,K53),0) | N53: =IF(ISNUMBER(G53),G53,Inputs!$B$24)/100 | O53: =100*(Inputs!$B$20*L53+Inputs!$B$21*M53+Inputs!$B$22*N53)*IF(F53="LOW",1-Inputs!$B$23,1) | P53: =RANK(O53,$O$5:$O$53)+COUNTIF($O$5:O52,O53)

Sheet Method
A1: How the numbers are set
A2: FINAL PRICE TARGET: the Quality @ 200-day routine's 3-method target (joint_price_targets.json):
A3: 1 Fundamental = next-year consensus EPS/EBITDA/sales x the stock's own 5-yr median multiples;
A4: 2 Robinhood mean analyst target; 3 median of dated major-firm analyst targets (<=120 days old).
A5: Final = median of three, average of two, or one alone. Agreement HIGH/MED/LOW = how close the methods are.
A6: SOXL and AAOX have no analyst coverage: their target is the 50-day SMA (first overhead resistance).
A7: SELL TARGET 1 = final target x Trim 1 %. Sell a third and re-check the thesis. A target hit is not an automatic exit.
A8: SELL TARGET 2 = final target x (1 + stretch). Sell the second third; the last third rides the trailing stop.
A9: DOWNSIDE REVIEW LEVEL = the higher of (60-day low less the buffer) and (cost less the max-loss %).
A10: Below it the trend has broken support: re-check the thesis and decide sell or hold. Not a stop order.
A11: TRAILING STOP: shown once price >= cost / (1 - trail %), i.e. +17.6% at 15%. = 60-day high x (1 - trail), never below cost.
A12: REWARD : RISK = (sell target 1 - price) / (price - review level). Above ~2 is a favourable hold.
... A33: The Quality @ 200-day routine (step 4f) refreshes joint_tracker_data.json and rebuilds this file each weekday. Edit blue cells for what-ifs; a rebuild overwrites them.
